{"ze_2012_p3":"世界末日：2012","ze_2021_xmas_world":"圣诞小镇","ze_203_Factory_b9":"203号生化工厂","ze_30_seconds__b21_p2":"30秒真男人","ze_666_crazy_escape_v2_4":"恶魔逃亡","ze_8bit_csgo2_fix":"俄罗斯方块之城大冒险","ze_abandoned_bio_bunker_v1_4":"废弃燃料惊魂","ze_abandoned_industry_va2":"废弃工厂","ze_abandoned_project_v1_2_csgo":"遗弃工程","ze_AcuticNotes_v1_2f":"技巧很重要","ze_aepp_nano_grid2_v1h":"电子游戏","ze_alchemy_b7":"神秘力量","ze_alien_mountain_escape_ffvii_v5_hdr":"外星人高山逃亡:最终幻想7","ze_alien_mountain_escape_p4":"外星阿里山","ze_alien_shooter_v7_ps4":"孤胆枪手","ze_alien_vs_predator_v6go_fix":"异形大战铁血战士","ze_alitur_v3":"最后的下水道","ze_amalgamation_v1_1":"混合","ze_Ancient_Wrath_v2_test27_g6t":"古代遗迹:生化金字塔","ze_angelbeats_guild_a1_fix2":"天使的心跳","ze_anima_ruins_v2_2":"灵魂废墟","ze_antartika_b2_csgo":"南极基地逃亡之旅","ze_anzalone_v3_fix":"安扎隆","ze_Aooka_v3_t6":"龙之殿","ze_aot_trost_v8":"进击的巨人:托洛斯特V7","ze_ApertureScience_p2":"光圈科技","ze_apocatastasis_v1_2":"最终剿匪","ze_Apollo_p2":"阿波罗登月计划","ze_aragami_v1_1":"竹星林月","ze_arcade_parade_b6":"街机小游戏","ze_arctic_escape_p2":"北地逃亡","ze_ardeca_revamp":"外星记录：安德科","ze_artika_base_v1_2":"探秘基地","ze_artika_base_v1_4":"阿提卡基地","ze_ashen_keep_p":"黑魂：灰烬堡垒","ze_assassins_creed_csgo":"刺客信条","ze_astral_v2_1_fix":"星夜城堡v2","ze_atix_apocalypse_p3":"守点防御系列：末日","ze_atix_panic_v1":"守点防御系列：恐慌","ze_atos_v2_3":"阿托斯","ze_Aurora_tower_v6_8":"极光塔传说","ze_Avalanche_Reboot_beta7_g3t":"重启雪崩计划【难】","ze_avalanche_reboot_beta7_p2":"重启雪崩计划","ze_aware_v1_2a":"觉醒","ze_azathoth_v1_1":"阿撒托斯","ze_aztecnoob_p2":"阿兹坎特遗迹","ze_aztec_temple_p2":"阿兹特克神庙","ze_A_E_S_T_H_E_T_I_C_v1_1":"舞台剧","ze_baboon_escape_v1_012":"猴子神庙历险记","ze_backrooms_p3":"密室逃脱","ze_barrage_p2":"逃离大坝","ze_Bathroom_v2_5":"浴室逃亡","ze_beyond_the_boundary_v1_4":"境界の彼方","ze_beyond_the_boundary_v1_5":"境界彼方","ze_bh3rd_v2_b3":"崩坏3测试版","ze_bholes_budhole_1_1":"我的温暖小屋","ze_bigfoot_escapeica_v3_4":"吸血鬼洞穴","ze_biohazard2_rpd_004_p3_fix2":"生化危机2：警察局","ze_biohazard2_sewer_004_p8":"生化危机2：下水道","ze_biohazard3_nemesis_b5_2":"生化危机3:复仇女神","ze_biohazard_manor_004_p4":"生化危机1：洋馆","ze_biomes_attack_b1_2":"生物群系","ze_bioshock_v6_2_csgo7":"生化奇兵","ze_bioshock_v7_1_csgo_a2":"生化奇兵","ze_bisounours_party_p2":"彩虹岛3","ze_blackmesa_escape_p4":"逃离黑山基地","ze_blocky_mess_b2":"混乱的方块","ze_bloodstrike_escape_v2":"血战逃生","ze_blood_castle_b7":"CSO血色古堡","ze_blue_magic_castle_v3_1":"蓝魔法城堡","ze_blue_zenith_v0_2":"蓝阳当空","ze_boacceho_p4":"古堡逃脱","ze_boatescape111_v1_1f":"小艇逃亡111之随机大挑战","ze_Boatescape_Ultimate_t2f1":"坐船终极大乱斗","ze_boredom_p":"无所事事","ze_bowser_in_the_fire_sea_v1e_rs2":"库巴城堡","ze_bp-infested-prison_p2":"越狱危机","ze_breakable_p3":"拆迁队","ze_bulhufas_a1_1":"布卢法斯","ze_bunker_escape_v1_2":"地堡逃亡","ze_cancer_gopnik_escape_v9_2":"病名为战斗民族","ze_candy_star_a3":"糖果星","ze_castlevania_64_v1_3_b9_go":"恶魔城外传","ze_castlevania_p1_7":"恶魔城","ze_castle_bridge_v1_4":"城堡大桥","ze_castle_of_the_bladekeeper_v1":"VIP之城","ze_ccc_ffvii_alien_reactor":"阿里炉","ze_ccc_floator_mislands_timantetrix_v2":"僵尸逃跑:迷失，回忆之地","ze_ccc_toastersand_v2":"混搭面包机","ze_chaos_v7_7":"大乱斗","ze_check_b1_1f":"西洋棋魂","ze_cheezylab_beta7":"地下研究所","ze_chemical_weapons_depot_v3a":"化学武器仓库","ze_Chicken_Lords_Tower_ig1":"小鸡城堡大逃亡","ze_chicken_ranch_v2_2":"鸡动力厂","ze_christmas_b2_1":"圣诞节","ze_christmas_infection_p2":"圣诞工厂","ze_chroma_v0_4_csgo5":"色调之形","ze_chrono_trigger_b3_fix5":"时空之轮","ze_chronus_a1":"柯罗诺斯","ze_clara_civitate_v3":"克劳拉城","ze_clockwork_v1d1":"时轮律动","ze_coastalcity_b10":"沿海城市","ze_codevein_v1_cm4":"嗜血代码","ze_collective_v1_8":"小地图大集合","ze_colorful_v2_4":"黑白的绚烂","ze_colorlicouspilar_p4":"色彩世界","ze_colors_p3":"多彩逃亡","ze_color_escape_b2":"色彩逃亡","ze_color_traps_beta2_4":"彩色陷阱逃亡","ze_complex_va3":"拿头逃生2","ze_conflict_v4_4":"公交车冲突","ze_contradiction_spiral_a2_2":"矛盾螺旋","ze_copy_escape_v2_3":"复制大逃亡【普】","ze_core_v2b":"熔火核心","ze_corrupted_bridge_b1_3":"毁坏大桥","ze_crashbandicoot_p3":"古惑狼","ze_crazykart_v4":"疯狂卡丁车","ze_crypt_v1_4":"墓穴","ze_crystal_a2":"晶状世界","ze_crystal_escape_v2_final":"水晶逃亡v1","ze_crystal_tower_a2":"水晶之塔","ze_csgo_grey2":"灰白大作战","ze_cso_decoy_v1_hdr":"CSOL大灾变","ze_cursed_bear_tales_v1_2":"诅咒熊传说","ze_cursed_ruins_v3":"遗迹逃亡","ze_CV_LOSII_Castle_Siege_b4":"洛西城堡：围攻","ze_CYBERDERP_p3_KIA":"魔化现实主义【普难】","ze_cyberia_v1":"网络世界","ze_cyberpunk_x_a07":"赛博朋克2077","ze_dangerous_waters_v1h_03_b":"危险的水域","ze_dangerous_waters_xmas_v2_4":"圣诞节危险水域","ze_danmaku_v1_5":"弹幕库","ze_dark_catharsis_v1_2":"神圣净化","ze_dark_souls_ptd_csgo2":"黑暗之魂","ze_Deadcore_s7f2":"死亡核心S","ze_deadly_crash_a2":"致命行动","ze_Dead_Planet_Escape_b10":"死星逃亡","ze_dear_v1":"月神宫殿","ze_deathinvain_palace_v2":"枉死城","ze_death_star_escape_v4_3_p2":"星球大战：死星","ze_Death_Valley_b2":"死亡山谷","ze_death_wish_v6":"穷途末路","ze_deepice_p3":"深冰","ze_defensepart_escape_go1":"学会找点守","ze_depths_b2":"冥城：孤军深入","ze_descent_into_cerberon_v1":"潜入神庙基地","ze_desert_fox_v7_6":"沙漠之狐","ze_Desperate_Soul_a9":"异闻录：绝望之灵【普难】","ze_destruction_of_exorath_v4_lite":"黑影空间","ze_dev_r4a_csgo4":"角落开黑","ze_dev_Reprise_v1_0":"身法考验","ze_diamond_cube_v1":"钻石魔方","ze_diddle_v3":"欺骗","ze_djinn_go1":"埃及神鬼图鉴","ze_doom3_v2":"毁灭战士3","ze_doomsday_bridge_v4":"末日大桥","ze_DOOM_p2":"毁灭战士","ze_Doorhug_and_Solo_v6_2_g1t":"贴门就能搜楼","ze_dragonball_snakeway_v2":"龙珠蛇道逃亡","ze_drakelord_castle_b3":"龙王城堡","ze_dreamin_v3_3":"梦想","ze_dungeon_of_ignorance_a1_2":"隐秘地牢","ze_dust_escape_p3":"沙漠逃生","ze_DYSTOPIA_a4":"反乌托邦","ze_easy_escape_r":"超级简单的逃亡","ze_eden_a3":"伊甸园","ze_egyptian_b5":"埃及人神图鉴","ze_egyptian_trip_v1_1":"埃及游记","ze_einstein_v7":"爱因斯坦的世界","ze_electrical_factory_b3_d":"发电站","ze_elevator_escape_p3":"电梯:逃出升天","ze_eos_forbidden_area_v1_81":"边境保卫战:EOS禁域","ze_Ep2_Plant_b1":"逃离!未来环境园","ze_epic_escape_v2_1":"史诗逃亡","ze_error_a0_ps":"错误","ze_escapetheworld_a33":"逃离异世界","ze_escape_cascade_b1":"新逃离地平线【咸】","ze_Escape_Citadel_r4":"17号都市要塞【咸】","ze_escape_horizon_p3":"逃离地平线","ze_escape_stroggos_p2":"逃离斯特罗戈","ze_escape_the_eye_p3":"逃离法眼","ze_eternal_grove_v3":"永恒之林","ze_eternal_journey_go_v1_4t11":"飞升者：永恒之旅","ze_eternal_void_p3":"永恒虚空","ze_event_ox_new_year_go2":"快乐就完事了","ze_evernight_a3_4":"永夜","ze_evil_mansion_v1_finalf":"整蛊豪宅","ze_exchange_innovation_v1bf":"逃离生化大楼","ze_fapescape_p5":"乐高","ze_fapescape_rote_v1_3":"乐高大逃亡:噩梦陷阱","ze_farmhouse_v9f2":"坦克农场V9f2","ze_fartlocker_escape":"陷阱逃生","ze_fast_escape_p2":"快跑！","ze_fcescape_b2":"游戏宅房","ze_ffuxx_demon_naramina_a2":"纳拉米娜雪域城堡","ze_FFVII_Cosmo_Canyon_v5k_fix":"最终幻想7：宇宙大峡谷","ze_ffvii_cosmo_canyon_v6test4":"最终幻想7：宇宙大峡谷v6","ze_FFVII_Mako_Reactor_v5_3_v5":"最终幻想7：魔光炉","ze_ffvii_mako_reactor_v6_b09k2":"FF7：壹号魔晄炉V6","ze_ffvii_malgo_reactor_v8_5":"最终幻想7:混搭魔光炉","ze_FFVII_Snow_Cosmo_v5_5f":"最终幻想7：雪域峡谷","ze_ffvii_temple_ancient_v4_3":"FF7:古代种神殿","ze_ffvii_temple_ancient_v5_2":"最终幻想7:古代种神殿","ze_ffxii_feywood_b3_1_x6":"最终幻想12：幻妖之森","ze_ffxii_feywood_b6_1k":"FF12：幻妖之森","ze_FFXII_Mt_Bur_Omisace_v5_4fix4":"最终幻想12：神都布尔奥米赛斯【","ze_FFXII_Paramina_Rift_v1_4_a8t":"最终幻想12：帕拉米亚","ze_ffxii_ridorana_cataract_t4_ps3":"最终幻想12：里多拉纳大瀑布","ze_FFXII_Ridorana_Cataract_t5_3_g3f":"最终幻想12：里多拉纳大瀑布","ze_FFXII_Salikawood_v1_6f":"最终幻想12:萨利卡树林","ze_ffxii_westersand_v7_z9":"FF12：西沙v7","ze_ffxii_westersand_v8zeta1_x18":"FF12：西沙v8","ze_FFXIV_Coil_of_Bahamut_v4_4":"最终幻想14:巴哈姆特大迷宫【神","ze_ffxiv_wanderers_palace_v2_va2":"最终幻想14:旅神圣域v2","ze_ffxiv_wanderers_palace_v4_va2":"最终幻想14:旅神圣域v4","ze_FFXIV_Wanderers_Palace_v5_2":"最终幻想14:放浪古神殿v5","ze_FFXIV_Wanderers_Palace_v6_2z1":"最终幻想14:放浪古神殿v6","ze_ffxxiii_westrcanoyn_f12xd_csgo2":"最终幻想7：西部","ze_firewall_laboratory_part1_p2":"防火墙实验室-其一","ze_firewall_laboratory_part2_p2":"防火墙实验室-其二","ze_fire_temple_v2_4":"火炎神庙","ze_floating_rocks_survival_csgo_v3":"浮空岛","ze_flowering_b10":"月神殿前传","ze_flower_a1_2_f":"花","ze_FLOWER_a3_1":"花","ze_flying_world_p":"空中世界","ze_fond_dream_h4":"南柯一梦","ze_football_go2":"甲级联赛-踢足球","ze_forbidden_repository_a1_4":"幽闭书库","ze_foreign_sand_mix_v2_fix":"魔改高山逃亡：沙暴精灵塔","ze_forestbunkers_v1_b3_e2":"森林惊魂","ze_forest_of_steel_z1_4":"钢铁之森","ze_forest_r_v1":"迷雾森林","ze_forhidden_slicoo_s3_fix":"缩略版禁地斯狄科","ze_forhidden_slicoo_v5":"禁地斯迪科","ze_forhidden_void_b5":"禁地虚空遗迹","ze_forsaken_temple_v3_b5":"被遗忘的神殿","ze_freespace_ultimate_b4":"闲置空间","ze_frostdrake_tower_v1":"冰龙高塔","ze_frozentemple_rc1_1":"冰封神庙","ze_frozen_abyss_v1_2":"冰封深渊","ze_funny_runner_v3_1":"娱乐赛跑","ze_gameshow_v1_2_csgo1":"游戏节目","ze_genso_of_last_v3_4_t1":"最后的幻想","ze_geometric_v1_4":"几何奥秘","ze_ggeasy_solo_win_v1_1":"混搭之城大冒险","ze_give_it_a_name_test4":"给这图起个名字","ze_gods_wrath_p2":"神の怒","ze_golubenkaya_meow_v1_2":"戈卢本卡亚的猫","ze_got_the_north_csgo3":"权力的游戏：北境","ze_grand_boatescape_p3":"圣船出航","ze_grau_a03_4f":"创世E_格劳","ze_great_crate_escape_v6":"货运码头","ze_greece_escape_p":"希腊逃亡","ze_greencity_fix":"绿之城","ze_grey_world_v1":"灰白世界","ze_gris_v1_13":"格里斯","ze_Halloween_House_b4":"万圣屋","ze_halo_ce_p1_b16":"光环:战斗进化","ze_halo_p3":"光环","ze_halo_poa_p4":"光环：战争进化","ze_halo_quarantine_zone_alpha_v6":"光环2:隔离区","ze_harry_potter_v2_1_csgo":"哈利波特","ze_Haste_to_flee_1b":"逃出生天","ze_haunted_lab_escape_p3":"闹鬼实验室","ze_hazard_escape_p2":"危机逃亡","ze_hello_world_v1":"你好，世界","ze_Hell_Escape_p2":"地狱逃亡","ze_hidden_fortress_p":"隐藏的堡垒","ze_hidden_temple_v2_5":"隐秘神庙","ze_hiems_facilities_v3ar_b7_rename":"冬季工厂特别行动","ze_highest_to_lowest_v1_1":"从上至下","ze_hive_complex_v1_2_1":"安布雷拉公司","ze_hl2_episodic_escape_f2":"半条命II : 17号城市","ze_hobbit_escape_b2":"(魔戒)霍比特人：哥布林人之战","ze_hold2_boring_b5":"学会断后","ze_hold_em_v8_f3":"坚守行动","ze_hollow_a2":"空洞","ze_honkai_impact_3rd_babel_v1_55":"崩坏3：巴比伦塔","ze_honkai_impact_3rd_cyberpunk_cityv26_7":"崩坏3：天穹市","ze_horizon_sky_escape_v2":"天际逃亡","ze_hsc_a4_q3":"hsc方块","ze_huge_labo_escape_b1_2":"高山基地逃亡","ze_hydroponic_garden_v1_1":"水培花园","ze_hypernova_v2fix":"超新星之旅","ze_iamlegend_p3":"我是传奇","ze_icecap_escape_v5_p":"西瓜橘子图","ze_icecap_solo_v1_f":"阴间版西瓜橘子","ze_iceland_escape_v1_2":"冰岛逃亡","ze_iceworld_athletic_b4_5":"冰天雪地竞技场","ze_ice_cavern_va4":"冰窟","ze_illusory_world_v4_5":"虚空幻境","ze_illya_b4_csgo_a3f":"伊利亚城之旅","ze_inboxed_final_fix":"抄袭CF","ze_indiana_jones_v4a_004_p4":"夺宝奇兵","ze_industrial_dejavu_p3":"工业循环","ze_infected_lab_v4_1":"龙珠实验室","ze_infected_sewers_csgo":"感染下水道","ze_infected_tramway_csgo1":"感染电车","ze_infernal_spire_p2":"地狱尖塔","ze_infested_industry_p2":"工业区大撤离","ze_infiltration_final_r1":"经典长征","ze_insanitycity_va2":"疯狂都市 Alpha2","ze_insensible_v9_6_fix":"感性之路","ze_interception_p2":"拦截行动","ze_Island_Escape_p3":"孤岛逃亡","ze_isla_nublar_p3":"侏罗纪公园：恐龙岛","ze_italy_town_p2":"意大利镇","ze_japans_3rd_bombing_v8":"最美日本","ze_jiangnan_town_v3":"江南水乡","ze_jiba_journey_v4_3":"羁绊之旅","ze_jjba_v7":"JOJO的奇妙哲学乐高","ze_johnny_nukem_go_b8_3a":"毁灭强尼","ze_journey_p4_1":"旅途","ze_jungle_escape_v1_2_d":"密林逃脱","ze_JurassicPark_Escape_p2":"侏罗纪公园2","ze_jurassicpark_evolved_v4":"侏罗纪公园：进化","ze_JurassicPark_p3":"侏罗纪公园","ze_jurassicpark_sg_final":"逃离侏罗纪公园","ze_jurassic_park_story_csgo":"侏罗纪公园的故事","ze_k19_escape_go1":"K19机库","ze_kaffe_escape_v2":"咖啡逃亡","ze_kage_a3":"赤影战士","ze_kf_bioticslab_a1":"生物实验室","ze_Kitchen_v2":"厨房逃亡","ze_komatsu_v3":"跳刀精英图","ze_kororinpa_v2_2":"转转球迷宫","ze_kraznov_poopata_p2":"天界方块之旅","ze_kuwei_0_12":"枯萎","ze_l0v0l_v1_4_csgo2":"颜文字1","ze_l4d2_c1m3_mall_csgo_v0_3_le":"求生之路2-购物中心","ze_laserend_v3":"跳刀结局图","ze_laser_escape_v1_1":"精简版跳刀列车","ze_laser_island_b6_8":"跳刀岛","ze_last_man_standing_p2":"一夫当关","ze_Last_Man_Standing_v6_T3":"拯救世界：一人之巅【神】","ze_legends_of_dawn_v1_6":"黎明传说","ze_legoland_crackheads_p2":"乐高传奇","ze_lemonysnickets_p2":"雷蒙·斯尼奇历险","ze_licciana_escape_zrgbr_b3":"陷阱跳刀岛3","ze_lightnight_v1_4fix_hdr":"夜空","ze_light_shadow_L1_4":"光与暗","ze_light_v7_csgo_tk13_v5_2fix":"911之光","ze_Lila_Panic_Escape_tr2":"里拉逃亡v3","ze_lolxd_final_fix_iswear_v3":"紫色世界v3","ze_lostclue_b3_3":"CSO异乱之战","ze_lost_v2_1":"失去","ze_LOTR_Helms_Deep_v5_p6":"魔戒2: 圣盔谷","ze_lotr_isengard_csgo1":"魔戒2：艾辛格","ze_LOTR_Laketown_v3_3":"魔戒：长湖镇","ze_LOTR_Minas_Tiret_p2":"魔戒：米纳斯议会","ze_lotr_minas_tirith_p5":"魔戒：米纳斯提利斯","ze_LOTR_Mines_of_Moria_p2":"魔戒1: 莫瑞亚矿坑","ze_LOTR_Mirkwood_v2_5":"魔戒黄金矿工","ze_LOTR_Mount_Doom_p3":"魔戒3: 末日火山","ze_luciddreams_f5_6":"清醒的梦【普】","ze_luck_matters_v3_1":"运气第一","ze_lucy_escape_v1":"樱花神殿","ze_LuigisMansion_p3":"路易基鬼屋","ze_lux_umbra_v1":"光与影前传","ze_L_The_Lower_v1_4":"艾罗之城第一部","ze_L_The_Medium_v1_6":"艾罗之城第二部","ze_m0w0m_csgo1":"颜文字(m0w0m)","ze_m0w0m_new_k2":"颜文字3","ze_mabinogi_f4_1":"洛奇","ze_madara_temple_v1fix_csgo":"斑神殿","ze_Madara_Temple_v1fix_ez":"宇智波斑神庙","ze_magala_castle_final":"马格拉城堡","ze_magic_carpet_p2":"魔毯","ze_magmadrake_b4":"炎龙高塔","ze_magus_v2_4":"麻瓜山","ze_mapeadores_museum_v1":"mapeadores博物馆","ze_mario_adventure_beta01_fix1":"马里奥的大冒险","ze_mario_tower_v4_p2":"马里奥高塔","ze_mars_escape_gp3":"火星大逃亡","ze_meatropolis_p2":"克苏鲁：血肉幻境","ze_megaman_x_2b_fix":"洛克人大冒险","ze_melong_dow_learjet_gp1":"里尔喷气机惊险逃亡","ze_metro2033_v1_fix_f1":"地铁2033","ze_mgden_y3_fix":"弹幕世界","ze_military_escape_p4":"军事基地","ze_MindTree_v1_6":"树之魂","ze_minecraft_adventure_v1_3d":"MC大冒险","ze_minecraft_escape_b3":"我的世界逃亡","ze_minecraft_run_a1_fix8":"我的世界大逃亡","ze_minecraft_universe_v1_5":"MC宇宙","ze_minecraft_v1_1_p3":"我的世界（小MC）","ze_minimal_csgo":"极病","ze_mirrors_edge_reborn_v4_2_p3_xfix":"镜之边缘：镜面逃脱","ze_misaka2_v1_3":"御坂大冒险2","ze_misaka_v1ff":"御坂大冒险","ze_Mission_1943_fix2":"任务：1943","ze_mist_q2":"雾城龙影","ze_Mixture_3de_v1f2_g1t":"cs1.6经典地图混搭逃亡","ze_mlgsurf_v1_3_4":"米垃圾滑翔","ze_mochi_island_f6":"年糕岛","ze_mojos_minigames_v1_4_1":"魔力小游戏","ze_moltentemple_csgo1":"熔岩神殿","ze_monochrome_v1f":"黑白幻境","ze_monolith_csgo":"被遗弃的研究基地","ze_moonshadow_ex_v4_1":"月影极限传说","ze_moon_base_p3":"月球基地","ze_motanuminc_sgfinal":"黑基佬传奇:护菊同盟","ze_mountainspire_p2":"高山逃亡","ze_mountain_escape_csgo2":"神图爬雪山","ze_mountain_escape_snow_v7_1":"爬雪山","ze_mytex_escape_v3_p":"MyteX逃亡","ze_m_g_e_b4_5":"音乐小游戏","ze_m_the_final_v1_4":"御坂大冒险（下）","ze_naiads_v4a_6f":"水泽仙女","ze_nameless_necropolis_v3":"虚无古墓【难】","ze_namviet_v6_1":"踩雷王","ze_naruto_p":"火影忍者","ze_Natural_v1_4":"自然神殿","ze_necromanteion_v3_1":"希腊神殿","ze_negative_legacy_va2":"消逝的遗物","ze_neglected_v2_2":"忽视","ze_neko_canyon_ps3":"尼高峡谷","ze_newyork_escape_v1":"纽约大逃亡","ze_nibui_a3_1a":"钝色之间","ze_nightmare_dimension_p3":"梦魇空间","ze_noir_p":"黑暗工厂","ze_nomada_h3":"多重花园","ze_noob_too_easy_v3_3a":"腥红绝界","ze_nora_v1_11":"诺拉","ze_nostromo_escape_p2":"诺斯托罗莫","ze_nostromo_redux_v1_2":"逃离空间站","ze_nothing_alpha2":"湮灭之城2","ze_notredame_p4":"逃离诺特丹","ze_no_name_v1_6":"全方位练习图2","ze_no_name_v2_3":"[弹幕]无名","ze_no_title_v2_5":"全方位练习图","ze_nuclear_site_survie_by_gm":"核遗址求生","ze_nuke_p5":"导弹基地逃亡","ze_NY_marathon_p2":"马拉松大追逐","ze_obj_blackout_b4":"Obj:封锁","ze_obj_insane_v1_2":"半条命：疯魔计划","ze_Obj_npst_v1_3fix":"Obj:黑山基地V1","ze_obj_npst_v2":"半条命：黑山计划V2","ze_Obj_Rampage_v1_2":"横空出世【难】","ze_Obj_Rescape_v1":"OBJ:浴火重生","ze_obj_vertigo_v3_1":"Obj:殒命大厦","ze_obj_void_b4_t2":"半条命：虚空计划","ze_oblivion_castle_v6":"遗忘城堡","ze_oblivion_mountain_b2k":"遗忘山谷","ze_ocean_base_escape_p2":"海洋基地","ze_offliner_v2_csgo1":"单机练习のking","ze_omega_p3":"欧米伽计划","ze_omen_090":"预兆 - 古数觉醒","ze_omochix_v3_2fix":"元素秘神","ze_oot_shadowtemple_b10":"塞尔达传说：时之笛","ze_opti_variety_missions_p3":"多样化任务","ze_otakuroom_v5_6_ps":"死宅房","ze_outbreak_v2_1_p":"爆发","ze_Outlast_v2_cm1_fix1":"逃生I【普】","ze_outpost_escape_k2":"前哨逃亡","ze_palace_adventure_v1_2":"宫殿神秘冒险","ze_palace_of_minolila_v1":"米诺莉拉神殿","ze_pallaroid_rage_v1":"帕拉诺伊德之怒","ze_pandora_evolution":"潘多拉-进化","ze_pandora_revolutionz_hdr2":"潘多拉","ze_panic_escape_v3_2_e5_hdr":"跳刀仓库","ze_paper_escaper_p7":"纸质世界","ze_paranoid_rezurrection_csgo1":"游乐园","ze_parkers_pit_p":"帕克矿坑","ze_Parking_p4":"停车场","ze_PC_v1_2":"电脑CPU求生【难】","ze_pd2_crime_art_v2":"收获日2：美术馆","ze_percocet_v5":"止痛","ze_peter_mansion_v1_p5":"恐怖公馆","ze_phantasy_escape_p3":"幻想逃亡","ze_pirates_port_royal_v4_2":"加勒比海盗：罗亚尔港v4","ze_Pirates_Port_Royal_v5_6":"加勒比海盗：罗亚尔港","ze_pitchblack_p2":"极黑逃亡","ze_pixel_fantasy_adv_b2_10":"幻想像素世界冒险","ze_pizzatime_v9":"披萨时间","ze_pkmn_adventure_v8_5d":"神奇宝贝冒险之旅v8","ze_pkmn_adventure_v9_3":"宝可梦对战","ze_platformer_b2":"捡币小游戏老版","ze_pokemon_adventure_v1_1":"口袋妖怪历险记","ze_Pokemon_Rivals_v1_8":"宠物小精灵：乱斗大作战","ze_polatrio_v1_1_hdr":"尼尔：图书馆","ze_Polyglot_f3":"阿尔芬城堡","ze_ponchermonkey_shooter_csgo1":"庞彻猴枪手","ze_portal_story_p2":"传送门故事","ze_PoR_island_p3":"岛屿大逃离","ze_postal_v1_1":"夺命邮差","ze_PotC_IV_p3":"加勒比海盗IV","ze_PotC_p4":"加勒比海盗","ze_Predator_Ultimate_p7":"铁血战士","ze_project_alcaria_x2":"阿卡利亚计划","ze_prototype_p2":"虐杀原形","ze_purgatorium_b1fix2":"涤罪炼狱","ze_puta_p3":"工厂逃亡","ze_quiver_v2a_f1":"震颤危机","ze_Rabanastre_Royal_t5":"最终幻想12：拉巴纳斯塔王都","ze_raccoon_facility_v6b_p":"生化危机：蜂巢","ze_radio_building_v1_3":"广播大楼","ze_rainbow_factory_v2":"彩虹工厂","ze_raintime1_torontoisland_v23":"时落之雨","ze_raintime1_torontoisland_v5x":"时落之雨(旧)","ze_raintime2_stormwindkeep_v3":"时雨2风暴守护者","ze_raintimex_code0_v22":"时落之雨X","ze_ramp_a1_1":"城堡遗迹","ze_randomizer_c1":"高手随机小游戏","ze_random_escape_csgo":"新卵蛋小游戏","ze_random_p2_fix":"随机小游戏","ze_Ratescape_v5_4":"玩具奇兵【神】","ze_rats_escape_final":"捕鼠记","ze_realm_f3":"意境","ze_reconnoiter_b5":"侦查行动","ze_ReflectBox_L":"陷阱逃亡图2","ze_reloaded_v1f":"合金装备","ze_resonance_cascade_p3_fix":"半条命：串联共振","ze_retribution_p2":"复仇行动","ze_Reverse_a03_f3":"镜像颠倒","ze_revue_starlight_v3":"少女歌剧院","ze_rev_a6_3":"俄罗斯方块","ze_re_creation_v2_25":"时空重铸","ze_re_surf_skyline_b0_11":"复刻之天际滑翔","ze_ripsuhdude_v1_6":"地下工厂","ze_river_escape_v3_fix_r1":"码头逃亡","ze_rizomata_a46":"精灵塔（上）","ze_rizomata_b45":"精灵塔（下）","ze_rockescape_go2_1":"石头世界","ze_rocket_escape_g1":"火箭逃离","ze_rooftop_madness_v1_9_csgo":"屋顶求生","ze_Rooftop_Runaway_Extended":"逃离屋顶加长版","ze_roof_adventure_v8f":"屋顶大冒险","ze_roof_adventure_v9":"屋顶大冒险v9: 逃出生天","ze_roscente_go1":"宇宙之光-罗森特","ze_RTCW_Ominous_Rumors_p4":"重返德军总部","ze_ruin_of_black_stone_v2":"黑石废墟【普难】","ze_ruminas_v12_f":"鲁米纳斯","ze_rush_B_v1_4":"rushB","ze_rush_B_v2_2":"rushB v2","ze_R_W_B_ulti":"红黑白的乐章","ze_sakuzyo_b2":"削除","ze_samsung_galaxy_v1_3":"这跳刀我上我也行","ze_sam_hd_v1_fix":"英雄萨姆","ze_SANCTUARY_v1_2":"圣城","ze_sandstorm_go_v1_5":"新沙尘暴","ze_sandstorm_v7_1_e4":"沙尘暴","ze_santassination_v3":"黑色行动-代号：圣诞","ze_saw_p3":"电锯惊魂","ze_scourge_k1":"祸乱之源","ze_scp_containment_breach_v1_b02_cm4":"scp研究所","ze_sc_turtles_v5_p2":"王八船","ze_seano_see_2g5":"玄之海","ze_secret_grimoires_b5":"魔法奥秘","ze_sele_a2_1":"海边圣堂","ze_serious_sam_tfe_v2_6":"英雄萨姆：首次出击","ze_serpentis_temple_csgo5":"美杜莎神庙","ze_serpentis_temple_v2a_csgo2":"美杜莎神庙","ze_SEVIIEN_a1":"未来花园","ze_sewage_processing_v8":"污水处理厂","ze_sewer_escape_p3":"下水道逃亡","ze_sewer_v2":"下水道","ze_sg1_missions_v2_1_p2":"星际之门","ze_shadow_corridor_v1_2":"影廊","ze_Shadow_temple_v4_4":"血影神殿","ze_shaun_of_the_dead_p":"僵尸肖恩","ze_shaurma_v3_b07_csgo":"苏卡不俩特","ze_showdown_v4_1_p":"对决","ze_ShroomForest2_p6":"蘑菇森林2","ze_ShroomForest3_p":"蘑菇森林3","ze_ShroomForest_p6":"蘑菇森林1","ze_Siberia_1990_v1_2c_p5":"西伯利亚大危机","ze_silent_hill_2_illusion_b5":"寂静岭：幻境","ze_silent_hill_3_dawn_full_t3":"寂静岭3：黎明（完整长征版）","ze_silent_hill_blackblood_f6":"寂静岭：黑血","ze_sit_caelum_paradisus_b7_hdr":"雕刻天堂","ze_skill_escape_v10":"KZ训练场","ze_skygarden_v2_1":"天穹树","ze_skyline_v1":"逃出生天","ze_Skyscraper_city_r2":"镜之边缘：大厦飞驰","ze_sky_athletic_adv_v9_13":"天空竞技","ze_sky_fantasy_v1_6":"天空幻想v1","ze_sky_fantasy_v2_1":"天空幻想","ze_sky_journey_v8":"天空旅途","ze_sky_temples_v3":"天空神庙","ze_slender_escape_rc2":"面条人：噩梦回忆","ze_snowescape_p2":"雪地逃亡","ze_somnium_illusione_t3":"精神分裂","ze_sonic_cityescape_beta1919_810":"索尼克城市逃亡","ze_sorrento_escape_v2":"索伦托","ze_spacestation_sgfix":"空间站","ze_space_flight_p3":"太空船逃亡","ze_square_r":"方形列阵","ze_sst2_p":"星河舰队2","ze_sst_b2_1_p5":"星河舰队","ze_stalkermonolit_v8gofix1":"潜行者：黑石特异区","ze_Stalker_Ultimate_v2_3_gg":"切尔诺贝利核电站","ze_stalker_ultimate_v4_9":"切尔诺贝利:躲猫猫","ze_standart_map_csgo_b1":"CS起源经典地图混搭","ze_stargate_escape_v8_p2":"星门传奇","ze_starwars_v2fix_csgo3":"星球大战","ze_star_wars_prequel_f1":"星球大战：前传","ze_stilshrine_of_miriam_v6_2":"最终幻想12：米利暗遗迹【神】","ze_stilshrine_of_miriam_v7_2fix":"FF12：米里亚姆神殿","ze_strange_escape_p2":"奇异逃亡","ze_suchirifu_v3_1_h":"斯基利弗树林迷宫","ze_SUMAI_facility_v1a":"速卖金字塔","ze_sunkentemple_v3_1":"魔兽世界:沉没神庙","ze_sunlight_p2":"日光","ze_supershitshow_a2":"超级爬山","ze_Super_Metroid_v4":"超级银河战士","ze_surface_a1_ps_b2":"矿井","ze_surf_bona_v1_3":"飘移滑翔","ze_surf_danger_p2":"国产滑翔","ze_surf_dark_fantasy_v2go2":"黑暗幻想","ze_surf_easy_v1_3":"简单的滑翔","ze_surf_facility_p4":"美国滑翔","ze_surf_froyo_lite_v2_4":"缩略版酸奶滑翔","ze_surf_froyo_v2_2":"酸奶滑翔","ze_surf_galaxy_zena_v4_2B4":"银河滑翔【滑】","ze_surf_gypt_v1_3_1f":"大金字塔滑翔","ze_surf_happy_b7":"快乐滑翔","ze_surf_inferno_003":"沙盒滑翔【滑】","ze_surf_inferno_v2_22":"沙盒滑翔","ze_surf_last_point_v1_5":"最终之战滑翔","ze_surf_next_step_v1_4":"滑翔下一步","ze_surf_outside_csgo1":"奥德赛滑翔","ze_surf_sahok_p3":"沙口滑翔","ze_surf_saltfish_csgo4":"咸鱼的滑翔","ze_surf_shonyudo_v1":"山涧幽谷滑翔旧版","ze_surf_shonyudo_v5_2":"山涧幽谷大滑翔","ze_surf_vortex_v2_6":"漩涡滑翔","ze_SURVIVORS_p2":"幸存者","ze_S_A_M_v1_7":"剑与魔法","ze_taboo_carnation_v2_ps2":"博尼塔尼亚半岛行动","ze_teletraan_v1":"变形金刚","ze_temple_escape_va3":"神庙逃亡","ze_temple_of_phantom_v1p_2":"幻影神殿","ze_temple_of_the_demon_god_v2":"恶魔神圣殿","ze_temple_raider_b4_ps6":"神庙急袭","ze_Temple_Run_v5":"神庙逃亡","ze_tenkinoko_welkin_v1_6f":"天气之子","ze_tesv_skyrim_v5_6":"上古卷轴5：天际","ze_texturescape_p2":"坑爹逃亡","ze_th06_scarletDevilMansion_a0c":"幻想乡：红魔馆","ze_thelostworld_redux_p2":"侏罗纪公园：失落世界","ze_thelostworld_v2_csgo":"失落的世界","ze_the_curse_of_blackwater_v6b":"黑水镇的诅咒","ze_the_last_chapter_v1_5":"终焉之章","ze_the_lost_tomb_b3_3_1":"失落的古墓","ze_the_new_era_of_crazy_escape_b7":"新疯狂大逃亡","ze_thousand_steps_gf1_2":"千步先走一步","ze_three_eyes_v1_1":"三眼","ze_thriller_escape_p":"惊悚逃亡","ze_tibia_v4_1":"探险卢克加德岛【普难】","ze_tilex_possession_v2_12":"列车逃亡","ze_tilex_ultimate_v2_13e":"列车逃亡终极版","ze_timesink_v1_2":"时空交错","ze_timesplitters_p2":"时空撕裂者","ze_titanic_escape_v2_3_fix1":"泰坦尼克号惊魂","ze_titan_souls_b1_8":"泰坦之魂","ze_tkara_v4_3":"塔卡拉地下基地","ze_tloz_stone_tower_temple_v1_4e":"塞尔达传说-石塔神庙","ze_toaster_p3":"面包机","ze_totally_new_wester_f":"最终幻想12：圣诞节西沙","ze_Totemo_Roka_v1":"洛卡之城","ze_touhou_gensokyo_o4":"东方幻想乡","ze_townscape_vfinallqfix2":"逃离小镇","ze_toy_world_final":"玩具世界","ze_traak_b2":"逃命游轮","ze_trainescape_final_p2":"火车逃亡","ze_trials_v1_4_hdr_test3":"天国审判","ze_tropico_escape_gf1_1":"热带岛屿逃亡","ze_turokbase_p3":"图罗克基地","ze_TV_station_r4":"电视台","ze_tyranny2_v1_csgo2":"暴君2","ze_tyranny_v5_go3":"暴君","ze_ubermenschen_b2":"虐杀原形:超凡者","ze_Uchiha_Legacy_cm2_fix":"宇智波庙","ze_ultimate_cancer_v1_1":"病名为战斗民族","ze_undercave_es_mi_v1_5":"地底洞穴","ze_underground_escape_p":"地下逃生通道","ze_underground_station_v3":"地铁逃亡","ze_undersea_temple_a4_4":"海底神殿","ze_undertale_g_v1_3_fix1":"传说之下：安黛因","ze_undertale_sans_final":"传说之下：sans","ze_undertunnel_escape_b5_csgo":"地下隧道逃生","ze_unknown_underground_a2_8_2":"未知的地下","ze_unknow_escape_v5":"神必逃亡","ze_unreasonable_sacrifice_v1_2_7":"不要当工具人","ze_uranus_attack_b4":"天熊下凡","ze_urbanterror_b2":"都市恐慌","ze_urban_laby_of_death_p2":"城市迷宫","ze_UT2004_Convoy_r5":"虚幻竞技场","ze_uyuni_v1_6":"天空之镜乌尤尼","ze_v0u0v_csgo1":"颜文字2","ze_valkvang_v1_2":"黑暗之魂：瓦尔克堡","ze_valleyescape_v1":"山谷逃亡","ze_variis_b1_4":"影子人","ze_venice_escape_p3":"威尼斯","ze_vertigo_militia_b1_3_14":"危楼逃兵","ze_vietnam_p3":"月爛：草丛树木会说话","ze_visional_chaos_d6":"幻视","ze_visualizer_v1_2":"监视者","ze_volcano_escape_p2":"火山逃亡","ze_voodoo_islands_p5":"巫毒岛","ze_war_v1_4":"天空争霸","ze_watagi_tunnel_v1_1":"钟乳洞外传:渡木隧道","ze_whothefuckiam_v2_4":"我是哪个","ze_worlds_v1_2":"世界大逃亡","ze_world_escapes_v1":"逃离世界","ze_wow_molten_core_t1_1":"熔火之心","ze_xiii_winslow_bank_v2_2fix_4":"金库惊魂","ze_yueyingchuanshuo_10_9_f3":"月影传说","ze_yurilnier_beta007_hdr":"神恩颂歌","ze_zakum":"冒险岛扎昆","ze_zk_fapescape_p3":"小乐高","ze_zk_mall_of_zombies_p2":"购物中心","ze_zombierig_p3":"僵尸钻井","ze_zombie_city_finalfix_ps2":"僵尸城市大对决","ze_zulu_v2":"祖鲁","kz_kzra_rocky":null,"kz_sz_goldenbean":null,"kz_shortcut_tx":null,"jb_cell_indicator_v2":null,"ze_obj_horizons_a2":"半条命：地平线计划","kz_bir_dont_fix":null,"ze_rooftop_runaway2_p":"屋顶逃亡2","ze_forgotten_facility_p3":"被遗忘的工厂","kz_kiwi_hym":null,"ze_aot_trost_v6_2r":"进击的巨人:托洛斯特区v6","de_inferno":"炼狱小镇","kz_frpt_journey_f":null,"kz_otakuroom":null,"jb_minecraft_beta_v3-5":null,"ze_boatescape_ultimate_t2f5":"坐船跑：终极版","kz_orangejuice_v2":null,"de_mirage":"荒漠迷城","ze_l0v0l_p":"颜文字1","ze_boatescape888_v1_8":"弹幕刷分888","jb_nsa_detainment_facility_0-4":null,"kz_kzro_speedcavescape":null,"kz_hb_3kliksphilip":null,"kz_sonder":null,"ze_surf_happy_2_newbie_village_v3":"快乐滑翔-新手村","kz_brickblock_v2":null,"kz_forchi":null,"kz_lionheart":null,"kz_xmas2009":null,"kz_hellinashop":null,"ze_oneiros_p":"奥内罗斯神殿","kz_slide_dydanhomon":null,"kz_concept":null,"kz_slide_kissa":null,"jb_undertale_v1b":null,"kz_rush2suck":null,"jb_spy_vs_spy_xmas":null,"kzpro_gull_pidr_reborn":null,"kz_another_climb_map":null,"ze_obj_infiltration_b3":"半条命：渗透计划","ze_lotr_helms_deep_v5_p6":"魔戒2：圣盔谷之战","kz_rcn_impermanence":null,"kz_stepup":null,"kz_heaven_od":null,"kz_communityjump3":null,"ba_jail_minecraftparty_v6":null,"ze_silent_hill_3_dawn_v2":"寂静岭：黎明","ze_lotr_minas_tiret_p2":"小米那斯提力斯","jb_kanker_v3":null,"kz_why":null,"kz_slide_piss":null,"kz_kzro_brickstgrass_v2":null,"kz_scum":null,"kz_loathe":null,"kz_bhop_communityjump2":null,"kz_luv_less":null,"kz_slowrun_global_fix":null,"kz_hek":null,"kz_kiwideath":null,"kz_envy":null,"jb_electric_razor_v2_defy":null,"kz_slide_purple_x":null,"kz_ancient_v3":null,"kz_bluehop_mq":null,"kz_kzra_morath":null,"ze_obj_rampage_v2":"半条命：暴走计划","kz_cabin_fix":null,"kz_bionic":null,"ze_hypernova_p2":"超新星","kz_itz_updown":null,"kz_openspace":null,"kz_conrun_scrub":null,"kz_sp1_kansopyon":null,"kz_coastline_fix":null,"kz_slide_svn_temple":null,"kz_slide_pisauva":null,"bkz_apricity_v3":null,"kz_reach_v2":null,"kz_zhop_son_fix":null,"kz_gloom":null,"kz_bhop_lj":null,"kz_erinome":null,"kz_slide_concrete":null,"kz_lego":null,"kz_dakow":null,"kz_divert":null,"kz_symbiosis_final":null,"kz_roman":null,"kz_rompenutrias_asheglado":null,"bkz_iota_v3":null,"kz_neon_portal":null,"kz_wafflehouse_h":null,"kz_micropenis":null,"kz_sandyhill_hoc":null,"kz_slide_cave":null,"kz_custos":null,"jb_corruption_v3o":null,"kz_gus_sct2":null,"kz_holyspace":null,"vnl_farewell_fix":null,"ze_surf_bona_v3":"bona滑翔","kz_hope":null,"ze_boatescape101_p":"坐船跑101","kz_2seasons_spring_final":null,"kz_structures":null,"kz_bhop_sakura":null,"bkz_goldbhop_csgo":null,"kz_catalyst_gfix":null,"kz_doveen":null,"bkz_caves_go":null,"ze_huge_labo_escape_b1_3":"逃离大型实验室","kz_procrastination_f":null,"kz_waterhole":null,"kz_how2slide_fix":null,"kz_sp1_blueconcrete":null,"kz_basics_b02":null,"xc_minecraft3_global":null,"kz_antiquity":null,"kz_gfy_devcastle":null,"kz_snowman_v2":null,"kz_cajou":null,"kz_aztec":null,"kz_hikari_od":null,"kz_woodstock_v2":null,"kz_prismus":null,"kz_adventure_v2":null,"ze_noir_p4":"黑色街道","xc_minecraft4":null,"kz_simple_sp":null,"de_nuke":"核子危机","cs_office":"办公室","de_dust2":"炙热沙城2","kz_neoncity_z":null,"kz_frozen_go":null,"kz_azure":null,"kz_beyond_fix":null,"kz_slidemap_fix":null,"kz_kiwitown":null,"kz_sp1_behold":null,"kz_hideous":null,"kz_akrh_warehouse_v3":null,"kz_pharaoh_csgo":null,"kz_sp1_rengapyon":null,"kz_anus":null,"kz_kiwi_lars":null,"kz_surf_blue":null,"kz_cereal":null,"kz_adeline":null,"kz_2fast":null,"kz_slide_isnt_kz":null,"kz_goquicklol_v2":null,"kz_moon_fix":null,"kz_dyd_ladderjumps":null,"kz_bhop_watertemple":null,"kz_frpt_bhop_minimal_f":null,"kz_goodluck_p":null,"kz_ladderall":null,"kz_kzra_undercastle":null,"kz_antharas":null,"kz_kat_colorblind":null,"kz_gobbledygook":null,"kz_sky_lake":null,"kz_bhop_zenith":null,"kz_synergy_x":null,"kz_sc_ruins":null,"kz_ahful":null,"kz_fused":null,"kz_strafehop_fix":null,"kz_cg_lighthops":null,"kz_lair":null,"kz_sxb_despacito":null,"kz_quadrablock":null,"kz_kzro_chairs":null,"kz_carp_v2":null,"kz_climb":null,"kz_imaginary_final":null,"kz_kzro_gohome":null,"bkz_bonus_z1":null,"kz_chinablock":null,"kz_slidebober":null,"kz_genesis":null,"kz_delphinium":null,"kz_opus":null,"kz_matilda_np":null,"ze_licciana_escape_p":"里西西亚那","kz_kzro_cavehole":null,"kz_thrombosis":null,"kz_blindcity_easy_fix":null,"kz_pharos_fix":null,"ze_ice_hold_p2":"旅馆防守","kz_kzro_2boxes1room":null,"kz_cargo":null,"kz_gallus":null,"kz_d_decompile":null,"kz_kzro_jaashs":null,"jb_clouds_beta02":null,"kz_slumpfrageous":null,"kz_slate":null,"kz_forgotten_fix":null,"kz_variety_fix":null,"jb_minecraftisyan":null,"ze_little_trip_k":"短途旅行","jb_parabellum_v2c":null,"kz_construction":null,"kz_kzra_skaxis":null,"kz_wasabi":null,"kz_ephemeral":null,"jb_firar":null,"kz_pamehcilc":null,"kz_date2":null,"kz_spaceladders_v2":null,"kz_skyhotel":null,"kz_sandstorm_ez":null,"ze_ut2004_convoy_r5":"虚幻竞技场","kz_fury":null,"kz_bananaysoda_v2":null,"ze_breezy_v6":"轻松断后听歌","ze_lotr_mines_of_moria_p2":"魔戒1：摩瑞亚矿坑","kz_longjumps_easy":null,"kz_bhop_dusk_go":null,"kz_hb_lowlita":null,"kz_quicksand":null,"kz_cousucks":null,"kz_cranking_the_hog":null,"skz_bananaysoda_2":null,"ze_overlord_a7":"骨王","kz_bhop_monsterjam":null,"bkz_fapzor":null,"ze_paradise_v2_csgo":"天堂岛","ze_icecap_escape_v5_sgfix":"西瓜橘子","kz_lavablock_global":null,"kz_mediumcastle":null,"kz_lazy":null,"de_submerged":"深海设施","kz_cf_slide":null,"kz_goldentabby":null,"kz_forgettable":null,"xc_powerblock_rc1":null,"kz_futureblock":null,"jb_alaska_contest":null,"ze_escape_citadel_r2":"半条命II：暗能城堡","kz_alpha":null,"kz_dishonest":null,"kz_autumn_valley_fix":null,"kz_atelectasis_sct":null,"kz_civilizations":null,"kz_frpt_bhop_agartha_f":null,"kz_something":null,"bkz_pogo":null,"kz_oasis":null,"kz_morestairs_msq":null,"kz_emblem":null,"kz_sp1_redconcrete":null,"kz_zhongbitu":null,"kz_colors_v2":null,"jb_placzabaw_minecraft":null,"xc_dreamland2":null,"kz_7in1":null,"jb_undertale_nicestate":null,"kz_sp1_hallwaybhop":null,"kz_dvn_redcarpet":null,"kz_11342":null,"ze_atix_helicopter_p":"守点防御系列：直升机","kz_void":null,"kz_beginnerblock_go":null,"bkz_sahara":null,"kz_bhop_nothing_go":null,"kz_souljaboy":null,"kz_slide_bozo":null,"ze_devil_may_cry_df1":"鬼泣","jb_fg_justizanstalt_v3":null,"kz_smb":null,"kz_kzse_aztectemple":null,"kz_buildings_final":null,"kz_alfie":null,"kz_canyon":null,"kz_w1_holiday":null,"kz_unity_u01":null,"kz_amber_od":null,"kz_desolate":null,"kz_summercliff2_go":null,"kz_everything":null,"kz_dethroned":null,"kz_nix_od":null,"kz_perfunctory":null,"kz_asteroid_field_go":null,"kz_eventide":null,"bkz_dontstop":null,"kz_green":null,"ze_rooftop_reborn_v3_2_p4":"城市跑酷重置版","bkz_impulse":null,"kz_obsidian":null,"kz_continuum":null,"kz_longjumps_space":null,"kz_backwards":null,"kz_bacho":null,"kz_epusbridge":null,"kz_metalrun_global":null,"kz_bing":null,"kz_sp1_katakana":null,"kz_overgrowth":null,"kz_21loop_final_fix":null,"kz_invision":null,"kz_village":null,"kz_burnished":null,"kz_kzro_bronea":null,"kz_alt_cargo":null,"kz_vnl_crimdaughter":null,"kz_vnl_crimstmas":null,"kz_cataclysm":null,"kz_16pillars":null,"kz_sp1_inverseblocks":null,"kz_itz_transcendent":null,"kz_xand":null,"ze_totemo_roka_v1":"神秘海域","xc_umbrella_global":null,"kz_eudora":null,"bkz_goldbhop_v2go":null,"kz_orbolution_v2":null,"kz_stepblock":null,"kz_superstructure":null,"kz_excape":null,"kz_alfama":null,"bkz_chillhop_go":null,"kz_chillin":null,"kz_pollution":null,"kz_exemplum_fix":null,"kz_railings":null,"kz_baxter":null,"bkz_cg_coldbhop":null,"kz_bombu":null,"kz_drops_od":null,"kz_chopchop":null,"mg_falling_guy_v2":"糖豆人","mg_lego_multigames_go_v6_2":"乐高V6_2","cs_agency":"办公大楼","ba_jail_electric_global":null,"mg_quepinator":"抢图有机会被夹死的小游戏","jb_glow_b1":null,"de_boyard":"博涯堡垒","kz_slide_era":null,"kz_comp_global":null,"kz_kzro_sunmountainset":null,"kz_slide_vaahtera":null,"kz_lume":null,"kz_mac":null,"kz_de_bhop":null,"kz_catharsis_global":null,"kz_emblem_bonus":null,"kz_za_tileblock":null,"kz_bhop_koki_niwa":null,"kz_tomb_fix":null,"kz_victoria":null,"kz_whereyoufrom":null,"kz_demonhours":null,"kz_dark_fury":null,"kz_goldenroad":null,"kz_littlerock_v2":null,"kz_lmn":null,"kz_sukblock_v2_fixed":null,"kz_weightless":null,"kz_ghs":null,"kz_chessblock":null,"kz_hillside":null,"kz_frpt_rutces":null,"kz_kzro_fastcliff":null,"kz_owtetad":null,"kz_fastmap":null,"kz_huber":null,"kz_violet_fix":null,"mg_yolo_multigames_v2_1":"爬柱子选地图小游戏","kz_kzro_slidesmear":null,"kz_cliffhanger_go_global":null,"mg_bhop_battle_zig_v2":"连跳刚枪","kz_kzro_skyrocks":null,"mg_pauls_teambattle_v3_p":"团队合作小游戏(建议OP在场游玩)","mg_meimaobing_multigames_v1_3_1":"没毛病小游戏","kz_alt_aztec":null,"kz_blindcity_hard_final":null,"kz_rockjungle_v2":null,"kz_kzinga_fixed":null,"kz_nyc_v1":null,"kz_kzro_mountainhaya":null,"kz_phamous":null,"kz_phaztec":null,"bkz_nocturns_blue_gfix":null,"ze_hold_em_v10_p":"鬼脸长廊","kz_skytower":null,"kz_psyk":null,"ze_obj_eliminate_b2":"半条命：清除计划","kz_minimal_combo":null,"kz_bored":null,"kz_4u_nature":null,"ze_rooftop_runaway1_p":"屋顶逃亡1","kz_experiment":null,"kz_gy_agitation":null,"mg_pushinfinite_v6":"二次元密室赛跑","kz_sqrdsucks":null,"kz_bhop_composure_f":null,"kz_gitgud_final":null,"kz_kzra_rockloy":null,"kz_edifice":null,"mg_otakutower_v5":"有密室的二次元塔","kz_sp1_xmas2021":null,"kz_maya":null,"mg_biggletower_retex_st1":"混战大楼","xc_fox_shrine_japan_fr":null,"ze_action_plan_hurricane_a2fix4_1":"飓风行动","mg_blank_lili_final":"莉莉小游戏","kz_kohze_sucks":null,"mg_skymgb12":"天空塔","kz_ascend_hv":null,"kz_kzra_slidepuf":null,"jb_prisonbreak_galaxy_v2e":null,"ze_obj_npst_v1_2":"半条命：黑山计划","ze_siberia_1990_p":"西伯利亚1990","kz_apiisnotresponding":null,"kz_kzro_sekiseibhop":null,"kz_bhop_mosaic_od2":null,"jb_airforce_basic_v0-2b":null,"ze_obj_npst_v1_4":"半条命：黑山计划","kz_afterlife":null,"kz_binseebak":null,"kz_sc_collapse":null,"jb_autumn_v2":null,"ze_blackmesa_remix_p2":"黑山基地","ze_obj_filth_v1":"半条命：污点计划","vnl_undefined":null,"kz_quickshot":null,"kz_sxb_misato":null,"kz_morebricks_msq":null,"mg_ski_mountain_resortv3":"滑雪v3","ze_motanuminc_p2":"光圈后日谈","kz_life_final":null,"ze_lotr_laketown_v3_3":"魔戒：长湖镇","kz_strun_mq":null,"kz_sloth":null,"kz_refuge":null,"kz_dzy_beyond_v2":null,"ze_rockescape_2013_v1_3_3":"爬岩山","kz_celestial":null,"kz_quixotic":null,"jb_dusts2_2018":null,"kz_high_socks":null,"kz_portalclimb":null,"kz_farm_v2":null,"jb_arcade_b4":"街机游戏厅","kz_sanctuary":null,"kz_stuff_final":null,"kz_default":null,"kz_cf_snakeskin":null,"jb_buyukisyan_son_deluxe":null,"jb_k1ngphoenix_b1":null,"kz_kzra_suhu":null,"ze_surgical_nightmare_v1_b2c":"手术室噩梦","kz_combohop_c02":null,"kz_ashen":null,"kz_island":null,"kz_bhop_lego":null,"kz_sp1_parallelblocks":null,"kz_choka_fix":null,"vnl_invasion":null,"kz_technical_difficulties":null,"jb_bravo72":null,"kz_cf_foliage":null,"mg_ski_mountain_v2_csgo":"滑雪v2","kz_cyb_adrenaline_fix":null,"mg_among_us_minigames_tfx1":"太空狼人杀小游戏","kz_arcturus":null,"kz_kzro_hardhoodoo":null,"xc_secret_valley_global_fix":null,"kz_crash_fix":null,"mg_pudding_multigames_v3_5":"草莓布丁","mg_jacs_multigame_v1fix":"跳着抢图会死小游戏","kz_bhop_proxy_null":null,"kz_inspired":null,"mg_nature_multigames_v2":"自然公园小游戏","kz_south":null,"kz_christmas_fix":null,"kz_progressive":null,"mg_neox_multigames":"BBQ烤肉","kz_holmu1":null,"kz_sp1_siedlungclimb":null,"kz_ladderdespair":null,"kz_headbongo":null,"mg_gruber_multigames_tfx1":null,"kz_fatigue_v2":null,"kz_arcadium":null,"kz_tribute":null,"kz_suomi":null,"kz_intercourse!":null,"kz_evilcorp":null,"ze_forius_just_run_p2":"只管跑！","kz_kzro_yaruna":null,"kz_divided":null,"kz_alouette_fix":null,"kz_antimony":null,"kz_yes":null,"kz_gfy_strawberry_":null,"kz_bigcastle":null,"bkz_measure":null,"kz_talmaniac":null,"kz_shell":null,"bkz_itz_h25l":null,"kz_zxp_interstellar_v2":null,"kz_rise":null,"kz_spiritblockv2":null,"kz_pendulum":null,"kz_breezeblocks":null,"kz_signs_v2":null,"kz_autobadges":null,"kz_cascade_v4":null,"kz_tangent":null,"kz_lost_marketplace_gfix":null,"kz_cellblock_go2":null,"kz_unmake":null,"kz_kzra_bars":null,"kz_pineforest_v2":null,"xc_nephilim":null,"kz_kays":null,"kz_kzra_whitesquare":null,"kz_nbdy_maps":null,"kz_innit":null,"kz_persona_is_a_furry":null,"kz_prefix_cliche":null,"kz_forestrace_go":null,"kz_retribution_v2_final":null,"kz_okaychamp":null,"kz_tranquillity":null,"kz_bounce":null,"kz_sc_surf":null,"kz_carpet":null,"kz_flabbergast":null,"kz_cheese":null,"kz_coronado_fix":null,"kz_spacemario_h":null,"kz_fastcombowombo_v2":null,"kz_remedy_v2":null,"kz_slide_or_dont":null,"kz_comboking7k":null,"kz_communityblock":null,"mg_50arenas_v2_3":"50角斗场","kz_paradise":null,"ze_platformer_b6":"捡币小游戏新版","mg_oaks_multigames_v3":"大木博士小游戏","blackwidow_ren":"黑色城镇","kz_rush2sk8":null,"kz_dust":null,"kz_pamxul_wip":null,"kz_prototype":null,"de_canals":"运河水城","ze_hiems_facilities_v3fix2":"冬日工厂","kz_betapmaps":null,"kz_bozo":null,"ze_undertale_g_v1_3":"传说之下 安黛因之战","kz_nymph":null,"kz_sendhelp_final":null,"kz_mess":null,"kz_f_salted_banana":null,"kz_tq":null,"kz_persona_is_a_dictator":null,"de_shortnuke":"核子危机","kz_ggurk":null,"ze_obj_collapse_b3fix":"半条命：瓦解计划","ze_shroomforest2_p6":"蘑菇森林2","de_ancient":"远古遗迹","kz_twister":null,"kz_gary":null,"ze_vertigo_militia_b1_3_12":"谍影迷云","kz_dale":null,"kz_camembert":null,"ze_obj_rampage_v1_2":"半条命：暴走计划","kz_retreat":null,"kz_bhop_mentalism":null,"kz_armored_core":null,"jb_mountaincraft_v2":null,"jb_buyukisyan_gece":null,"kz_kzro_smallcanyon":null,"de_inferno_night":"午夜小镇","ze_honkai_nagazoracity_beta_4":"崩坏3：长空市","ze_dangerous_waters_v2_final":"危险水域","jb_mist_v1":null,"jb_centerperks":null,"kz_blatherskite_v1":null,"kz_sn_desert":null,"kz_ickkck":null,"kz_hate":null,"kz_microwave":null,"jb_spy_vs_spy_beta7":null,"kz_exps_cursedjourney":null,"kz_moorerutan":null,"kz_research":null,"kz_hammer":null,"ba_jail_electric_revamp_f2":null,"kz_fas2map":null,"kz_cuberunfast":null,"kz_kzro_tamlair":null,"kz_2seasons_winter_final":null,"kz_bible_black":null,"kz_shaft_fix":null,"kz_spire":null,"kz_automata":null,"kz_dank_stacks":null,"kz_avalon":null,"kz_kzra_coast":null,"kz_milehigh":null,"jb_arctic_jail_v3":null,"kz_cg_brick_rmk":null,"kz_prolific":null,"kz_loftroofs":null,"kz_frenzy":null,"jb_chicken_island":null,"kz_iluvprok_global":null,"kz_hb_anduu":null,"kz_portal_fix":null,"kz_hitech":null,"jb_wasdzone_v2_fix":null,"kz_dejavu":null,"jb_spy_vs_spy_beta_v1-2-3":null,"kz_porridge":null,"kz_legoland":null,"kz_toughluck_fix":null,"ze_titanic_escape_p2":"泰坦尼克号","kz_quadrant_fix":null,"kz_conrun_mq":null,"bkz_levite_v2":null,"bkz_lewlysex":null,"kz_abstruse_od2":null,"kz_comp_2022":null,"kz_winterize":null,"kz_avoria":null,"kz_ikea2":null,"kz_district_d01":null,"kz_leto_v2":null,"kz_arbitrary_words":null,"kz_smallmap":null,"kz_wafflehouse_x":null,"ze_mountain_escape_snow_v7":"雪山逃亡v7","bkz_cauz_final":null,"ze_tilex_ultimate_v2_13_thdr":"跳刀列车","ze_emerald_b3_f1":"翡翠之心","kz_kogamaostry":null,"kz_kzra_cliffy":null,"ze_antfarm_2v":"蚂蚁农场","kz_sp1_perf2win":null,"kz_surf_ace":null,"kz_thinkblock":null,"ze_boatescape999_v5":"跳刀刷分999","kz_paintball_tv_fix":null,"kz_arrebol":null,"kz_synthesis_v2":null,"kz_toonrun_final":null,"kz_scicret":null,"mg_dreamy_mariogames_b9":"疯狂跳绳马里奥","kz_yanse":null,"kz_machinery":null,"kz_overjoyed":null,"kz_kiwimirific":null,"kz_basicnoon":null,"kz_msp_comatose":null,"kz_slide_pallokala":null,"kz_psytime_go":null,"kz_cheetos_fix":null,"kz_giantbean":null,"kz_floatingislands":null,"kz_daniel":null,"kz_rumzor":null,"kz_theaquila":null,"kz_illusion_gfix":null,"kz_kzra_greycliff":null,"kz_sp1_candles":null,"ze_alien_shooter_gp1_3":"孤胆枪手","mg_fno_multigame_csgoverq_final":"4个传送门小游戏","jb_buyukisyan_son":null,"de_chalice":"圣杯村庄","de_studio":"工作室","kz_verv3_gg":null,"kz_devon":null,"kz_sp1_vines":null,"kz_talltreeforest_v3":null,"kz_kzra_hohum":null,"kz_piranha":null,"kz_cf_hestia":null,"kz_diajonal":null,"skz_sequence_shot":null,"kz_slide_koira":null,"kz_nebula":null,"kz_magus":null,"kz_zaloopazxc":null,"kz_janpu_final_fix":null,"kz_dungeon":null,"kz_sandstone_mq":null,"kz_hydromancy":null,"kz_gkd_v2":null,"kz_smallcastle":null,"kz_ambition":null,"kz_free_ahful":null,"kz_lust":null,"kz_serenity":null,"kz_moonlight":null,"kz_foggywarehouse_v2":null,"kz_ronja":null,"ze_starcraft2":null,"kz_sp1_greyhollowrock":null,"kz_allure":null,"kz_bhop_skyworld_go":null,"mg_cs_multigames_v1_3":"CS经典小游戏","kz_lookout":null,"mg_4all_multigamesq3":"4类小游戏","mg_arenamaker_b5_1":"自己家自己造","kz_list_gnida_v2":null,"kz_twilight_od":null,"ze_shroomforest_p6":"蘑菇森林1","kz_hb_smieszneznaczki":null,"ze_outlast_v2_cm1_fix1":"逃生","kz_woodstonegrass_final":null,"kz_gonbe":null,"kz_plains":null,"kz_eimeristzurueck":null,"kz_kzro_basalt":null,"kzpro_justrun_sp":null,"kz_holdmyhand":null,"kz_jg_ditch":null,"kz_xmas2020":null,"kz_bhop_benchmark":null,"kz_sp1_uchuunookuheki":null,"kz_cybersand":null,"kz_dzy_reach_v2":null,"kz_haki_v2":null,"kz_motivated":null,"kz_sxb_poi":null,"kz_slide_leto":null,"kz_generic":null,"kz_doubletake":null,"ze_obj_rescape_v1":"半条命：逃脱计划","mg_skilled_or_lucky_multigames_v1":"技巧还是运气","jb_dragons_lair_v2_defy":null,"kz_j2s_tetris_go":null,"kz_blackness":null,"ze_survivors_p2":"幸存者故事","jb_summer_jail_v3":null,"kz_freezing_ridge":null,"kz_glassesospa_v1":null,"kz_tour_de_nuke_rt":null,"kz_beanguy_v2":null,"ze_yueyingchuanshuo_11_1":"月影传说","ze_hell_escape_p2":"地狱逃亡","kz_dvn_cube_fixed":null,"kz_sp1_spreadblocks":null,"kz_kzro_greybrickbhop":null,"jb_kwejsi_v4":null,"kz_natureblock_scte":null,"kz_unnamed":null,"jb_legobels_corp_v1d":null,"kz_terablock":null,"de_cache":"死城之谜","ze_zombiemod_corporation_p2":"僵尸公司","kz_warehouse":null,"kz_sxb_makabaka":null,"bkz_hellokitty_v2":null,"kz_dryness":null,"ze_obj_nirvana_v1fix":"半条命：涅槃计划","ba_jail_futurouta":null,"kz_dvn_dull":null,"kz_bluerace_v2":null,"kz_nomibo":null,"kz_gfy_tech":null,"de_train":"列车停放站","ship_ren":"CF运输船","ze_ep2_plant_b1":"未来环境园","kz_levels":null,"kz_castlehops_v3":null,"kz_hyroblock":null,"kz_kiwifactory":null,"kz_alien_city":null,"jb_bigmt":null,"kz_lovesick":null,"kz_kzro_darkhole":null,"kz_dimensions_v1":null,"kz_after_agitation_easy_fix":null,"kz_rocks_global":null,"kz_correguachin_reisido":null,"kz_final_ascension":null,"kz_unity_collab":null,"kz_ehcivec":null,"kz_symmetry":null,"kz_surf_kim_hana_gl":null,"ze_thousand_steps_b7":"千阶之战","kz_moorish":null,"vnl_simplebrickrooms":null,"kz_auuughh":null,"kz_rcn_optimisery":null,"kz_psychosomatic":null,"kz_bhop_essence":null,"kz_kiwi_cod":null,"kz_bluuu":null,"kz_minimountain_f":null,"kz_boomblock":null,"kz_grass_hard":null,"kz_kzro_justgrab":null,"kz_flying_rabbits":null,"xc_karo4":null,"kz_ladderhell_fix":null,"kz_mz":null,"kz_ziggurath_final":null,"kz_adv_cursedjourney":null,"mg_submachine_multiarenas_remakeq_final_fix":"随机武器地图混战","kz_crysis":null,"kz_whatever_v2":null,"ze_jurassicpark_escape_p2":"侏罗纪公园","mg_3as_v1":"CS经典VIP","mg_weapon_gacha_v3_1":"随缘靠运气","ze_nik_allinone_p":"坐船剿匪","vnl_lea":null,"de_tuscan_b2":"托斯卡纳v2","mg_swag_multigames_v7_1":"史瓦格","jb_midi_sonic_v1":null,"mg_dev_evo_multigamesq":"梦幻进化","kz_toonadventure_go":null,"de_inferno_but_actually_no":"我不是炼狱小镇","kz_heatvents_mq":null,"kz_nightfall":null,"kz_wetbricks":null,"bkz_blackrockshooter_vzp":null,"fy_iceworld":"1.6雪地","kz_olympus":null,"vnl_oy_lj":null,"de_festival":"新年广场","kz_bridge17_fix":null,"kz_sunstone":null,"jb_snow":null,"ze_potc_p4":"小加勒比","jb_lego_jail_v8_fix":null,"jb_space_jail_sg":null,"mg_mario_party_v3_5":"马里奥派对","kz_splifff":null,"ze_best_korea_v1":"最美朝鲜","mg_weapon_case_arenas_v1_2":"开箱拼枪","kz_trazodon_fix":null,"de_hive":"蜂巢研究所","de_calavera":"亡灵乐土","ze_s_a_m_v1_7":"刀剑神域","ze_obj_vertigo_v3_2":"半条命：殒命计划","kz_euclide_illusionary":null,"kz_atlantis_od3":null,"ze_rizomata_va2":"精灵塔","kz_yoink":null,"kz_hb_lrs":null,"mg_arcs_multigames_v4":"跑酷抢图小游戏V4","kz_abandoned":null,"kz_ltt":null,"kz_conspiracy":null,"kz_unknownspace":null,"ze_games_v2_1":"小游戏","kz_bhop_horseshit_9":null,"kz_mescaline_f":null,"ze_aperturescience_p2":"光圈科技","kz_rectangle":null,"kz_byrem":null,"kz_return":null,"kz_zxp_final4":null,"kz_banjo":null,"kz_bhop_northface":null,"kz_vnl_crimdaddy":null,"kz_glide":null,"ze_surf_outside_b1_10":"奥德赛滑翔","ze_rien_z2_1f":"虚无幻界","kz_shark_gc":null,"kz_andromeda":null,"ze_black_lion_p2":"黑狮游泳池","kz_johndoe":null,"kz_memento":null,"kz_woodworld":null,"kz_skybridge":null,"kz_kareful":null,"kz_caulis_v2":null,"kz_megabhop_v2":null,"kz_bhop_badges2":null,"kz_gigablock_go":null,"kz_frpt_trip":null,"mg_skytower_cloudsky_v6_ldr":"天空塔","mg_creative_multigames":"创意小游戏","de_basalt":"冰火岛","de_cache_mirror":null,"ba_junglejail_v3":null,"kz_jump_n_run":null,"kz_rockclimb":null,"bkz_evanstep":null,"kz_synergy_ez":null,"kz_antigeneric":null,"kz_kiwislide":null,"kz_perf_darkcave":null,"kz_tmnf_e05":null,"de_not_mirage":"我不是荒漠迷城","kz_crypt_final":null,"mg_junglecamp":"丛林突袭","kz_egyptianbox":null,"kz_xiaobitu":null,"ze_apollo_p2":"阿波罗","kz_kzro_beknowater":null,"kz_layercake":null,"mg_labyrinth_game_b1":"恐怖迷宫","kz_sp1_whiteblocks":null,"kz_sp1_greyconcrete":null,"ze_re_lightshadow_v1":"光与影","vnl_ll_nuke":null,"mg_murasakichaos_multigames_v3n":"生化危鸡","mg_cs007_roadwars_fix03":"开车创人","mg_hellz_multigame_csgo_beta":"躲柱子抢图小游戏","kz_mushrruption_v8":null,"ze_light_shadow_l1_4":"光与影","kz_gfy_final":null,"bkz_zephyr_v2":null,"ze_collective_v1_9":"Luffarenの集思广益","kz_duality_v2":null,"ze_lux_umbra_v1_4":"光与影前传","kz_twiivo":null,"ze_ny_marathon_p2":"马拉松","kz_complex":null,"kz_kzro_cavernste_v2":null,"kz_bhop_rotebal3":null,"ze_darker_ruins_v1":"黑暗废墟","kz_kzro_mountainroad":null,"kz_kiwiqualia":null,"kz_citadel":null,"kz_carbon":null,"kz_kzro_shima_v2":null,"ze_luciddreams_csgo3":"清醒梦","xc_dtt_nasty_go":null,"kz_acores":null,"ze_mist_q3":"雾城龙影","kz_kzra_slidely":null,"kz_xmas2008":null,"mg_n64_goldeneye_goqfq2":"黄金眼","ze_naiads_v4a_5f":"水泽仙女","kz_kzro_mountainbhop":null,"kz_nieh":null,"kz_sp1_castaway":null,"mg_fun_matrix_trilogie_tfx1":"黑客帝国","ze_siberia_1990_v1_2c_p5":"西伯利亚1990","kz_minimalism":null,"ze_aoraitsu_r6f":"油桶世界","bkz_kartrider":null,"kz_8b1_brickngrass":null,"kz_kzro_mountainsein":null,"mg_battle_multigames_v1":"游乐园","kz_bhop_badges3":null,"ze_silent_hill_3_flee_v4":"寂静岭：逃离","ze_neron_v1_1":"幻境遗愿","kz_nightmare_v2":null,"kz_lastwork_p2":null,"ze_lab_v5":"实验室","kz_sp1_strafechallenger_ez":null,"ze_chicken_lords_tower_ig1":"小鸡城堡","kz_pantheism_p02":null,"mg_arcs_multigames_csgo_v2":"跑酷抢图小游戏","kz_comboya":null,"kz_igneous":null,"kz_gfy_fortroca":null,"kz_lego_two_redux_v3":null,"kz_j2s_cupblock_go_fix2":null,"ze_retribution_pf":"美国大兵开车图","ze_pools_b1_2":"Level130-荒谬游泳馆","ze_potc_iv_p3":"加勒比：不老泉","kz_asphyxiate":null,"cs_backalley":"后巷","kz_sp1_kyuubisroom":null,"kz_failed_fastrun_rt":null,"kz_athena":null,"kz_spacus":null,"kz_splopkopsc_loverick":null,"kz_cartooncastle_go":null,"de_shortdust":"沙城激突","xc_supermario_go_gfix":null,"vnl_whiterun":null,"kz_bhop_lucid":null,"kz_slide_0x7_n1m0":null,"kz_luonto":null,"ze_visualizer_v2_1":"深渊凝望者","bkz_cauz_short":null,"ze_hammer_bunker_part1":"锤子地堡","kz_sxb_biewan":null,"ze_ffvii_mako_reactor_v5_3_v5":"FF7：壹号魔晄炉v5","kz_ext_bblocks":null,"kz_weebfactory_censored":null,"kz_nuclear":null,"kz_slide_svn_extreme":null,"kz_peak_global":null,"cs_thunder":"霹雳行动","kz_reverse":null,"ze_luigismansion_p3":"路易基鬼屋","bkz_uninspired_trash":null,"ze_lego_m1":"马乐高","de_shipped":"运输货船","ze_watagi_tunnel_v2_1":"渡木隧道","ze_bathroom_v2_5":"浴室","de_seaside":"海滨危机","kz_gfy_c0mb0king":null,"kz_greyorgray":null,"kz_kzra_stonebhop":null,"kz_depot":null,"kz_glow":null,"kz_ominous2":null,"de_rails":"铁路站场","de_season":"四季公司","jb_moonjail_v2":null,"de_elysion":"极乐净土","bkz_canadaszn":null,"kz_lastwork_p1":null,"xc_alt_nephilim":null,"kz_zoomer_fix":null,"ze_surf_shonyudo_v6_1_final_fix":"沖津滑翔","kz_mike_v4":null,"ze_ancient_wrath_v2_test27_m5":"古代种","kz_insomnia_fix":null,"ze_tenkinoko_welkin_v1_7f":"天气之子：苍穹","kz_stranded":null,"kz_echo":null,"ze_por_island_p3":"POR刷分岛","kz_sp1_redbrickbhop":null,"mg_headshot_machine_multiarenas_v7":"爆头机器","ze_jurassicpark_p3":"侏罗纪公园","bkz_volcanohop":null,"kz_project":null,"kz_solidarity_v2":null,"kz_delirium":null,"de_ruby":"红宝石酒镇","jb_skyscraper_go":null,"jb_kanker_v1":null,"kz_man_everest_go_fix":null,"kz_linoleum":null,"kz_blockhardy2k":null,"kz_mandelbrot":null,"kz_gfy_blueberry":null,"kz_eilrahc":null,"ze_doom_p2":"毁灭战士","kz_zxp_undia":null,"kz_func_detail_v2":null,"kz_swamped_v3":null,"ze_serpentis_temple_p2":"美杜莎神殿","kz_ea_beneath":null,"kz_kukkojapallokidutus":null,"kz_p1":null,"skz_map":null,"kz_malignom_short":null,"kz_wafflehouse_easy":null,"mg_criticals_slaughter_maze_remake":"迷宫抢枪混战","ze_arcana_heart_v1_5":"圣灵之心","kz_halicarnassus_fs":null,"mg_ipods_all_in_one_final":"ipod小游戏","ze_obj_blackout_v1":"半条命：黑视计划","de_coast":"海滨古镇","kz_slide_red":null,"kz_sp1_shouryokou":null,"kz_kiwionerous":null,"kz_11735":null,"ze_boatescapex_b8":"坐船跑X","ze_deadcore_k3":"死亡核心","mg_skillixx_multigames_v2_csgo_sfixed":"技巧评价小游戏","kz_simplicity_v2":null,"kz_sp1_greenconcrete":null,"ze_neko_canyon_p3":"尼欧峡谷","mg_hype2":"很多小鸡的小游戏","kz_slide_wasteland":null,"jb_iron_go":null,"kz_zhop_freestyle":null,"mg_bhop_battle_space":"太空连跳决斗","ze_antartika_p3":"南极基地","kzpro_concrete_c02":null,"kz_checkmate":null,"xc_cliffjump_fix":null,"kz_conifer":null,"kz_redline":null,"ze_ocean_heart_v1":"海洋之心","ze_stardust_a03":"星尘","de_zen_v1_2":"樱花寺庙","kz_aaaa":null,"kz_internatus":null,"kz_question":null,"xc_lucid_global":null,"bkz_cakewalk":null,"kz_module":null,"mg_minecraft_castle_v3":"我的世界城堡","kz_streetblock":null,"mg_alphabox":"透明盒子","kz_slide_deee":null,"jb_canceris_beta3a":null,"kz_hoist_fix":null,"mg_lt_galaxy_csgo_v1pfix":"星系小游戏","mg_rank_multigames_final_fix":"段位小游戏","mg_watertower_retex":null,"ze_forhidden_void_b6_4":"禁地虚空遗迹","kz_kzra_oddland":null,"kz_techtonic_v2_ldr":null,"kz_nature_remaster":null,"jb_freierhimmel_v3":null,"mg_kirbys_brawl_v2":"星之卡比刚枪","kz_aether_fix":null,"kz_bhop_algetic":null,"kz_silk":null,"kz_modernvomit":null,"ze_rtcw_ominous_rumors_p4":"重返德军总部","kz_kzra_voovblock":null,"kz_sp1_purpose":null,"kz_sxb_remake":null,"ze_solidarity_paper":"纸质基地","kz_colorcat":null,"ze_pokemon_rivals_v1_8":"宝可梦竞技场","jb_quake_a03":null,"ba_jail_voodoo_v5":null,"mg_cutie_multigames_v1b":"彩虹跑道赛跑","skz_makalaka":null,"kz_hb_fyksen":null,"kz_eros_v2":null,"de_bank":"金库危机","ba_jail_prison_m_v6":null,"kz_cratespeed":null,"xc_skycastle":null,"kz_kzra_stoneishbhop":null,"kz_alice_fix":null,"kz_cdr_myst":null,"kz_simplyhard":null,"kz_combobreaker":null,"ze_desert_fox_v7_6f":"沙漠之狐","kz_monstrosity":null,"kz_sp1_aoirobhop":null,"kz_tron_global":null,"bkz_dydhop":null,"kz_j2s_westbl0ck":null,"kz_nightcastle":null,"mg_awp_submarine_v4csgo":"打苍蝇","kz_kzro_wallblocks":null,"kz_prekeeper":null,"kz_emptiness":null,"kz_vittu_mika_persse":null,"kz_concretejungle":null,"kz_nassau":null,"kz_rlk":null,"kz_colorcode":null,"ze_melong_dow_learjet_p3":"喷气机逃亡","kz_tense":null,"kz_bhop_exodus":null,"cs_italy":"意大利小镇","mg_pushcircle_csgo_remake_v1_5b":null,"mg_joes_multifunq2":"手雷打苍蝇","kz_bloodline":null,"kz_vci_apprentice":null,"kz_pixelrun_v2":null,"ze_lotr_mount_doom_p3":"魔戒3：末日火山","kz_trashsurf":null,"kz_bhop_slide":null,"kz_hemochromatosis":null,"kz_refract":null,"kz_gfy_limit":null,"bkz_greed":null,"kz_difficultas_discendi":null,"kz_sp1_bloodyljs_v2":null,"vnl_sewers":null,"de_gwalior":"瓜廖尔堡","ba_jail_anttidea_a095":null,"kz_rarkovosis":null,"ze_uchiha_legacy_cm2":"宇智波遗迹","kz_kzro_whiterock":null,"ze_ffvii_cosmo_canyon_v5k_fix":"FF7：宇宙峡谷","ze_grau_a03_4ff":"格劳","ze_meatropolis_p4":"血肉幻境","ze_neochrome_csgo3a":"霓铬","mg_koga73_multigames_h":"有吃鸡的小游戏","bkz_underground_crypt_v3":null,"ze_rooftop_runaway3_v2":"屋顶逃亡3","kz_timescape_zero":null,"de_tuscan":"托斯卡纳","ze_ffxii_mt_bur_omisace_v5_k3":"FF12：神都布尔奥米赛斯","ze_island_escape_p3":"小岛逃亡","kz_oldstuff":null,"kz_simplejourney":null,"de_cbble_old":"老古堡","ze_bisounours_party_go_v3fix":"彩虹岛","mg_copter_tower_v1":"直升机大战","kz_xmas2022":null,"ze_parkour_k":"跑酷公园","kz_cdr_rustenborg":null,"kz_fastcombomap":null,"de_austria":"静谧雪村","mg_cuberunner_csgo_v8":"方块障碍赛跑","kz_sp1_strafechampion":null,"kz_fabrik":null,"kz_kzro_hexonay":null,"bkz_fear4":null,"vnl_slidegarden":null,"kz_kiwiexultation":null,"kz_mazemerized":null,"de_nuclear":"CF潜艇","kz_brightblock":null,"kz_epiphany_v2":null,"kz_birrita_fix":null,"de_blagai":"布拉盖修道院","kz_edp445":null,"skz_odious_v2":null,"kz_dystopia_h":null,"kz_sxb_xbcmzl":null,"kz_hb_bacon":null,"kz_cdr_slash_final":null,"kz_kzro_syotiles":null,"kz_exoteric":null,"kz_sp1_hiragana":null,"de_engage":"车展大厅","de_not_dust2":"我不是炙热沙城2","cs_assault":"仓库突击","jb_electric_todestrakt_v18":null,"jb_minestriker_b4":null,"kz_dabitu_fix2":null,"kz_ladderhorror":null,"kz_haste":null,"kz_oloramasa":null,"kz_dontjump":null,"kz_kiwimind":null,"skz_sati":null,"kz_cthulhu":null,"kz_megalodon":null,"kz_lovely":null,"kz_purgatory":null,"de_reef":"滨海小镇","kz_erbajerb":null,"ze_acuticnotes_v1_2f":"尖音符","kz_ggsh":null,"kz_egyptmap":null,"kz_kiwitech":null,"kz_noobfort":null,"kz_fikablock":null,"kz_sp1_driedblocks":null,"kz_sp1_saishuu":null,"ze_boatescape_extendido_p4":"经典坐船：剿匪","kz_prima":null,"kz_lionharder":null,"de_airportbeta10":"机场","mg_pirateshipfight":"海盗短喷对决","kz_xtremeblock_v2":null,"kz_quick7_v2":null,"de_safehouse":"安全处所","de_dust":"炙热沙城1","ze_mirrors_edge_reborn_p3":"镜之边缘-重生","kz_highland":null,"ze_ffxii_mt_bur_omisace_v6_beta6":"FF12：神都布尔奥米赛斯","kz_wafflehouse_hard":null,"ze_random_p2":"随机卵蛋小游戏","ze_skyscraper_city_r2":"镜之城","kz_zhop_function3":null,"kz_nb_final":null,"ba_jail_alcatraz_redux_go":null,"jb_jail_bravo":null,"kz_gluttony":null,"kz_sp1_rockcanyonblocks":null,"de_prime":"悬河钻场","de_anubis":"阿努比斯","ze_cyberspace_v1":"赛博空间","de_aztec16":"阿兹特克遗迹(1.6)","kz_chloroplast":null,"de_ali":"阿里镇","ze_juice_a0_0":"果汁逃亡","kz_maxine":null,"kz_slide_rovod":null,"kz_crate_delight_go":null,"mg_multigames_devine_is_french":"假船沙鹰","kz_420b":null,"ze_tv_station_r4":"电视台逃亡","kz_altum_od":null,"cs_militia":"佣兵训练营","kz_chunky_peanut_butter":null,"ze_aot_trost_v8_3":"进击的巨人:托洛斯特区v8","kz_kzro_excitedbhop":null,"kz_galaxy_go2":null,"de_abbey":"修道院","jb_buyukisyan_dark":null,"jb_delta_9_kb_rage":null,"kz_ghat":null,"vnl_caverun":null,"de_inferno_old":"老炼狱小镇","kz_kzro_cryscosrun":null,"xc_minecraft2_global":null,"ze_ravenholm_a3":"半条命：莱温霍姆","ze_halo_ce_p1_c7":"光环","de_stmarc":"圣马克镇","de_extraction":"湖心别墅","de_eagleeye":"CF鹰眼","mg_pushcircle_doc_game_fix":null,"kz_redemption_csgo":null,"ze_rollermine_factory_2010_p":"滚动工厂","kz_chrysoprase":null,"de_overpass":"死亡游乐园","de_vertigo":"殒命大厦","de_nuke_mirror":"镜像核子危机","de_dust2_classic":null,"kz_surf_abaddon":null,"ze_slackerino_mapperino_v4":"FF12：黎铎拉纳大瀑布","de_stgellert":"盖勒特酒店","cs_downtown":"商业中心","de_santorini":"圣托尼亚","de_swamp":"失落沼泽","de_mutiny":"红帆要塞","cf_port":"CF港口","ze_lila_panic_escape_tr2":"打熊传说","jb_pyrenees_v1_2":null,"kz_hypothermia":null,"mg_just_multigames_v4":"天坠方块小游戏","bkz_measure2_b03":null,"kz_pianoclimb_go":null,"mg_mikis_multigames2":"捡钱买枪","kz_kzra_fustcaves":null,"ze_pidaras_va2":"屌图","kz_hb_fafnir":null,"kz_blocks2006":null,"kz_angina_final":null,"ze_halloween_house_b4":"万圣屋","kz_kzra_shortclimb_v2":null,"de_guard":"守卫所","de_castle":"绝壁城堡","de_vostok_esc8":"沃斯托克小镇","dm_shutdown":"废弃工厂","jb_synergy_v3e":null,"jb_delta_9_final_rage":null,"kz_tradeblock_go":null,"ze_zengcheng_fix":"广州增城","ze_illya_b4_csgo_a3":"伊利亚城","kz_rainrun_kn_f":null,"kz_slide_arid":null,"kz_babycat_fix":null,"mg_raphi_multigame":"滑水抢图小游戏","mg_hakenkreuz":"CF幽灵狼穴","jb_pleaseworkv420a":null,"mg_tv_tower_ace":null,"kz_mieszaneuczucia":null,"cs_insertion":"突入点","de_jingshen":null,"mg_square_tower_v2":null,"ze_mars_escape_p4":"火星逃亡","mg_16_battles_csgo":"16战斗","mg_clouds_multigames_v22":"云的游戏","jb_lost_planet_redux_v1b":null,"mg_twisted_theme_multigames_v1_4":"关灯躲方块","mg_lego_multigames_r1c1":"乐高r1c1","mg_thc_lego_multimap_v5":"乐高音乐房","mg_fozz_multigames":"彩色很亮的小游戏","kz_sandbox":null,"mg_tomgreens_allinone_tfx1":"游泳抢图小游戏","kz_erratum_v2":null,"mg_weapon_noob_v3_4":"有跳刀的小游戏","mg_race_long_road_ia2copyninjaq_final":"赛跑拿枪","de_aztec":"阿兹特克遗迹","ze_ffxii_ridorana_cataract_t5_3_g3f":"FF12：黎铎拉纳大瀑布","mg_fun2_multigames_csgoq":"管道抢图小游戏","ze_ffxii_paramina_rift_v1_4_a8t":"FF12：帕拉米娜大峡谷","ze_bioshock_v6_2_csgo6":"生化奇兵","ze_a_e_s_t_h_e_t_i_c_v1_1":"舞台剧","ba_jail_future_v2a":null,"jb_buyukisyan_dark_new":null,"jb_mario_in_jail_v1":null,"kz_kiwiexophoric":null,"mg_velocity_tower_csgo_v1":null,"ze_pc_v1_2":"巨人机箱","kz_kzro_hardvalley":null,"ze_kitchen_v2":"巨人厨房","cs_apollo":"阿波罗","ze_journey_p4":"黑魂：旅途","mg_potatogames_alpha0_1_d2":"马铃薯小游戏","ba_jail_electric_vip_csgo":null,"ba_jail_ds_alcatraz":null,"skz_pride":null,"mg_skeet_multigames_v7":null,"mg_crash_bandicoot_party_go_4":"崩溃派对","kz_meander":null,"mg_alex_multigames":"埃里克斯小游戏","ze_surf_virtus_b1_2":"病毒滑翔","kz_excavate_b":null,"kzpro_psilocybin":null,"jb_pipeline":null,"kz_betterdunjun":null,"mg_gh_multigames_final":"彩色按钮小游戏","mg_minecraft_multigames_v4":"我的世界V4","ze_stalker_ultimate_v2_3_gg":"切尔诺贝利核电站","ze_natural_v1_4":"自然","jb_sides_b1d":null,"mg_randomizer_csgo_v2":"随机小游戏","mg_sky_dustq2":"滑沙混战","jb_tacoroonies_v2_opt":null,"jb_lactose_intolerant_v3":null,"mg_grands_multigames_v2":"粉色天空小游戏","mg_fun_allinone_csgo":"简化版黄金眼","ze_genso_of_last_v4_b1":"最后的幻想乡","kz_surf_larry":null,"kz_sp1_icecave":null,"ze_pirates_port_royal_v5_6":"加勒比海盗：皇家海港","mg_123kill_v2":"123开打!","kz_kzro_mountainsnow":null,"mg_piratewars_island":"海盗船大战","mg_jump_for_gun_rd_v2":"躲障碍拿枪","mg_battle_slider":"障碍赛跑","kz_vnl_crimson":null,"ze_sky_athletic_adv_v9_12":"天空竞技场","mg_wl_multigames_tfx2":"永远的沙鹰1V1","de_bazaar":"中东集市","mg_football_csgo_v2":"足球精英","jb_hotel_beta_v3":null,"ba_jail_midi_gregor_v7":null,"kz_slowerrun":null,"mg_color_multigames_v2_fix_d":"多彩小游戏","de_cbble":"古堡激战","ze_shroomforest3_p":"蘑菇森林3","de_marquis":"马奎斯城","de_zoo":"动物园","cs_insertion2":"突入点2","jb_mist_nws":null,"vnl_cat":null,"mg_randomizer_reborn_v2":"随机小游戏 重生","mg_misty_island_multigames_v7":"天空之岛","kz_gemischte_gefuehlslagen":null,"ze_animu_v2_final":"动漫塔","ze_desperate_soul_a10":"绝望灵魂","kz_drunkards":null,"de_blackgold":"黑金钻井","ba_jail_container_v2":null,"mg_eparlana_multigame_v4":"抢图变八重樱小游戏","jb_cs4frags_remake":null,"mg_xm1014lover_multigames_v3":"素世小游戏","mg_rats_cuisine_v6":"老鼠的决斗(混战图)","cs_rush":"丛林突袭","ba_jail_ds_keimusho_v2":null,"kz_kiwipsychosis":null,"ze_chroma_k1":"异次元杀阵","de_mocha":"摩卡小镇","ba_jail_bh_wakka_1a":null,"jb_summer_jail_v2":null,"mg_radiotower_remake_v2":null,"mg_osacs_bumpminearena":"弹射器大战","mg_super_tower_aneq":null,"jb_bigmt_b2":null,"ze_easy_escape_v4":"EZZE","mg_galaxy_multigames_v5":"星空刀战1V1","mg_struses_games_v4_1":null,"de_ruins":"玛雅遗址","jb_paradise_prison_fix":null,"jb_k1ngleviathan_b3":null,"ze_aooka_v3_t6":"龙之殿","mg_lt_glacier_v3":"滑冰赛跑跳远","ze_mindtree_v1_6":"智慧树","ze_rush_b_v1_4":"RUSH B","ze_aurora_tower_v6_8":"极光塔","jb_crazyjump_new_beta1":null,"de_pitstop":"赛车维修站","ze_chandrila_go1":"星战:钱德里拉","ba_jail_electric_egoist_beta3":null,"ba_jail_e-block_fix":null,"ba_jail_lockdown_final_v2-5":null,"mg_krane_multigames_v_1_3":"踩方块抢图","ze_incident_seasons_b2":"四季异变章","de_lake":"湖畔激战","jb_portnoys_domain_go_v1d":null,"jb_nm_kistroll_b1b":null,"kzpro_wrath":null,"ba_jail_chernobyl_day":null,"jb_millennium_lega":null,"mg_speedrunner_csgo_v2_3_swbs":"跳火圈赛跑","de_mirage_mirror":null,"jb_arctic_summer":null,"de_chlorine":"科洛林","mg_turvassa_multigames_csgofix":"选位置等死小游戏","jb_prison_architect_v1":null,"kz_spacemario_xt":null,"mg_operationsunv11_1":null,"kz_kiwiterror":null,"ze_zertinan_v1_4":"FF12 : 泽尔提南洞窟","mg_nx-multigames_mbreal_beta":"不太好玩的小游戏","mg_mikis_multigames_rcs":"选图要有身法的小游戏","jb_carceris_021":null,"mg_noob_weapon_multiple_b2":"找彩蛋随机武器混战","ze_endless_dream_v1_2":"梦无止境","mg_unlucky_multigames_tfx1":"寻找马桶大作战","jb_obama_v5_beta":null,"ba_jail_texture_city_v2_1":null,"ze_ratescape_v5_4":"MLG的巨人房间","de_overgrown":"荒废船坞","jb_mayan_v1final":null,"ze_2049_v1_1":"公元2049","de_sugarcane":"蔗糖工厂","jb_finalattackrider_v3":null,"ze_parking_p4":"停车场","jb_shapeshifter":null,"jb_dusty_v1":null,"ze_core_v2a":"熔火核心","ze_sandstorm_go_v1_5x3":"沙尘暴","ba_jb_kajoly_fixed":null,"jb_jail_rebellion_fix":null,"jb_overcooked":null,"jb_moti2_final2":null,"de_biome":"热带村落","ba_jail_medieval_csgo":null,"jb_marioworld_rsc":null,"de_cornerwork":"旺角街头","mg_kyxnya_rfix":"巨人厨房","jb_peanut_v3r":null,"jb_tropico":null,"ze_skygarden_v2_3":"天穹树","ze_squid_game_v1":"鱿鱼游戏","ba_jail_modern_castle_csgo":null,"jb_lone_v1":null,"jb_citrus_final_hex":null,"ze_fapescape_katrina_v1_7":"乐高：卡特琳娜","jb_new_chernobyl_pu_fixed":null,"ze_death_valley_b2":"死亡谷","jb_cntrat_v2":null,"jb_corruption_v1y":null,"jb_oasisv07":null,"jb_subtropical_v1":null,"ze_border_b2_fix":"边境","ba_jail_reloaded":null,"ze_halo_quarantine_zone_alpha_v5":"光环2：隔离区","ze_binary_z4_1":"镜像时空回廊","mg_rainbow_multigames_v1":"彩虹小游戏","ze_ffxiv_wanderers_palace_v4_10":"FF14：放浪古神殿V4","de_mist":"雾隐雷达站","jb_atski_beta":null,"mg_speed_domination_2011_v02a":"高速抢点混战","cs_climb":"攀岩运动馆","cs_cruise":"凶厄游轮","mg_fun_hexa":"10个小游戏","de_ravine":"霜夜城堡","de_favela":"决战贫民窟","ba_dreamjail_watchtower_v2-1":null,"mg_brawlstars_multigames_v1":null,"mg_bombardment_v1":"手雷大战","ze_uranus_attack_v1":"保卫熊星","ze_kebab_immigrant_k":"少吃甜食","jb_astroriot_finish":null,"jb_vice_v1":null,"ze_scp_containment_breach_k1":"SCP：收容失效","ze_8bit_csgo3":"8位机","jb_arctic_jail_v1":null,"de_subzero":"极寒之境","ze_sanctuary_v1_2":"救世圣堂","ze_predator_ultimate_p7":"铁血战士","ze_dystopia_a4":"衰败城市","ze_fe8_sacred_stones_v1_4":"火焰纹章：圣魔光石","mg_thc_lego_v3fix":"乐高呱呱叫","cs_workout":"健身中心","ze_endemic_v1_3":"最终呼叫","ze_draco_accidere_v4_final":"天龙坠落","ze_bioluminescent_k1":"生物幽光","de_breach":"坦根特公司","mg_damons_headshot_contest":"随机武器爆头刚枪","jb_newyorkcity_competition3":null,"ba_jail_stronghold":null,"jb_kucukisyan":null,"jb_colorjail_v4_fix":null,"ba_arizona_2c":null,"ze_monolith_p":"异度神召Ⅳ-要塞","jb_water_prison_go_v3n":null,"jb_space":null,"ze_descent_into_cerberon_b2":"地狱突袭","jb_kniv_rainbow_v2":null,"jb_avalanche_csgo_b6":null,"jb_longstreet":null,"ze_reloaded_v1_ez2":"合金装备","jb_newera_b3":null,"ze_shrek_swamp_v3":"史莱克的恶臭沼泽","jb_killerbeta_xmas":null,"mg_modernworld_multigames_v1":"摩登世界小游戏","jb_favorite_map":null,"ze_trend_machine_2_v1_25_f":"风暴之主:阿尔法与欧米茄","de_facade":"正面突击","jb_lone_v2":null,"jb_playorrebel":null,"ze_polyglot_f3":"阿尔芬城堡","jb_fairway_csgo_yuna":null,"jb_mangaroons_prison_bh_v5":null,"jb_last_encounter_csgo":null,"ba_jail_campus_2015":null,"ba_jail_summer_bh_fix3":null,"ze_tibia_v4_2":"卢克加德岛","ze_underdeep_go_v1a":"夺命深渊","jb_temple_studios":null,"jb_canceris_v2":null,"jb_saverno_v2":null,"ba_jail_future_v1d":null,"ze_avalanche_reboot_k1":"代号 - 雪崩行动","ze_aztecorum_hc1":"阿兹章鱼特克","ba_jail_escapetrain":null,"ze_sumai_facility_v1a":"烧麦工厂","ba_jail_farmville":null,"jb_f1rst_beta1":null,"jb_moti_fix":null,"jb_moti_fix2":null,"ba_jail_electric_revamp_final":null,"ze_dev_r4a_d_csgo2":"俄罗斯方块逃亡","jb_finland":null,"jb_mangaroons_prison_bh":null,"jb_renegade_v3":null,"jb_shmetro_v4":null,"jb_space_jail_sgnws":null,"ze_super_metroid_v4":"超银河战士","jb_legendfun_son":null,"ze_biohazard3_nemesis_b6_2":"生化危机3：复仇女神","jb_lego_jail_v8":null,"ze_suchirifu_v3_h":"斯基利弗树林迷宫","ze_cv_losii_castle_siege_b4":"洛溪城攻防战","jb_industry_beta03":null,"jb_sektoroyuncutoplulugu":null,"ba_jail_canyondam_go":null,"jb_plainsight_v1":null,"ze_verdant_k":"翠幕遁影","ba_jail_hellsgamers_go_v1":null,"ba_jail_mini_gregor_v5":null,"jb_fortify_v2-2":null,"ba_jail_ds_pripyat":null,"jb_augment_v2":null,"jb_fentex_fix":null,"jb_meows_rats":null,"jb_notch_sly_beta1":null,"jb_hogwarts_fix":null,"jb_shmetro_beta_v7":null,"jb_citrus_v2":null,"jb_serene_autumn":null,"ze_purgatorium_m":"炼狱","jb_minebrother":null,"jb_clouds_final5":null,"ba_jail_ds_desertstorm_v2":null,"jb_rumble2":null,"ze_hobbit_escape_b4c":"霍比特人","ze_temple_run_v5":"逃离神庙","jb_august_2k17_v1c":null,"jb_cyber_isyantimi_v2":null,"jb_parone_lnz":null,"jb_summer_mixalot_v1n":null,"ba_jail_sunrise_v3":null,"ba_jail_electric_razor_go":null,"ba_jail_ds_seaside_v0":null,"jb_tric":null,"jb_blank_b4":null,"jb_eckz_dee_v1c":null,"ba_xg_starline_v1_1":null,"jb_summer_mixalot_v1m":null,"jb_neon_mansion_v2-2":null,"jb_august_2k17_v1b":null,"jb_alien_final":null,"jb_boxer_th":null,"ze_cyberderp_p3_kia":"赛博世界","jb_waterside_v4":null,"kz_wafflehouse_ez":null,"kz_skariz_brainhard_go":null}
